{"deployed": {"mapPin71328238": ["crossbow", "crossbow"], "mapPin71328233": ["crossbow", "crossbow"], "mapPin70404238": ["crossbow", "crossbow"], "mapPin71328265": ["crossbow", "crossbow"], "mapPin70893889": ["field", "garden"], "mapPin71216440": ["field", "pottedplant"], "mapPin70893848": ["field", "garden"], "mapPin69530589": ["field", "pottedplant"], "mapPin71328261": ["crossbow", "crossbow"], "mapPin70845713": ["crossbow", "crossbow"], "mapPin71613245": ["crossbow", "crossbow"], "mapPin71315902": ["crossbow", "crossbow"], "mapPin58065515": ["crossbow", "crossbow"], "mapPin69628750": ["crossbow", "crossbow"], "mapPin69086617": ["crossbow", "crossbow"], "mapPin60067473": ["crossbow", "crossbow"], "mapPin65774575": ["field", "pottedplant"], "mapPin71444547": ["virtual_red", "virtual_red"], "mapPin69832193": ["virtual_red", "virtual_red"], "mapPin71352934": ["field", "pottedplant"], "mapPin71302390": ["field", "pottedplant"], "mapPin69855408": ["virtual_red", "virtual_red"], "mapPin70892636": ["field", "pottedplant"], "mapPin69837601": ["crossbow", "crossbow"], "mapPin71610968": ["crossbow", "crossbow"], "mapPin71611843": ["crossbow", "crossbow"], "mapPin69884739": ["crossbow", "crossbow"], "mapPin71462144": ["poivirtualgarden", "poivirtualgarden"], "mapPin59227683": ["crossbow", "crossbow"], "mapPin54043248": ["crossbow", "crossbow"], "mapPin68169759": ["crossbow", "crossbow"], "mapPin69440548": ["field", "pottedplant"], "mapPin71445965": ["virtual_scarlet", "virtual_scarlet"], "mapPin72012227": ["virtual_red", "virtual_red"], "mapPin69700526": ["virtual_scarlet", "virtual_scarlet"], "mapPin47872662": ["field", "garden"], "mapPin72374851": ["virtual_red", "virtual_red"], "mapPin71135807": ["virtual_red", "virtual_red"], "mapPin70342061": ["virtual_red", "virtual_red"], "mapPin50455187": ["field", "pottedplant"], "mapPin71350536": ["crossbow", "crossbow"], "mapPin54641920": ["crossbow", "crossbow"], "mapPin71614357": ["crossbow", "crossbow"], "mapPin69390491": ["virtual_black", "virtual_black"], "mapPin71167035": ["virtual_dandelion", "virtual_dandelion"], "mapPin71167022": ["virtual_dandelion", "virtual_dandelion"], "mapPin70845717": ["virtual_black", "virtual_black"], "mapPin71167052": ["virtual_black", "virtual_black"], "mapPin71227929": ["crossbow", "crossbow"], "mapPin71167027": ["virtual_dandelion", "virtual_dandelion"], "mapPin65380674": ["virtual_red", "virtual_red"], "mapPin70895507": ["virtual_black", "virtual_black"], "mapPin71618705": ["virtual_scarlet", "virtual_scarlet"], "mapPin70901359": ["virtual_scarlet", "virtual_scarlet"], "mapPin71617834": ["virtual_red", "virtual_red"], "mapPin71613503": ["virtual_black", "virtual_black"], "mapPin69031289": ["virtual_red", "virtual_red"], "mapPin70896780": ["virtual_dandelion", "virtual_dandelion"], "mapPin66634046": ["crossbow", "crossbow"], "mapPin71217103": ["crossbow", "crossbow"], "mapPin71473955": ["virtual_dandelion", "virtual_dandelion"], "mapPin62590873": ["virtual_dandelion", "virtual_dandelion"], "mapPin70487080": ["virtual_black", "virtual_black"], "mapPin68194934": ["virtual_black", "virtual_black"], "mapPin70132456": ["virtual_black", "virtual_black"], "mapPin71622195": ["virtual_dandelion", "virtual_dandelion"], "mapPin71622154": ["virtual_dandelion", "virtual_dandelion"], "mapPin69689703": ["virtual_black", "virtual_black"], "mapPin71424221": ["virtual_black", "virtual_black"], "mapPin70486531": ["virtual_black", "virtual_black"], "mapPin71435918": ["virtual_dandelion", "virtual_dandelion"], "mapPin65879904": ["virtual_black", "virtual_black"], "mapPin70411901": ["virtual_scarlet", "virtual_scarlet"], "mapPin71436247": ["carnationseed", "carnation"], "mapPin66814868": ["carnationseed", "yellowcarnationblossom"], "mapPin65900416": ["carnationseed", "carnation"], "mapPin71438199": ["virtual_red", "virtual_red"], "mapPin65380675": ["virtual_dandelion", "virtual_dandelion"], "mapPin71612979": ["virtual_dandelion", "virtual_dandelion"], "mapPin71607800": ["virtual_black", "virtual_black"], "mapPin71637895": ["virtual_dandelion", "virtual_dandelion"], "mapPin65659731": ["virtual_black", "virtual_black"], "mapPin71418012": ["virtual_dandelion", "virtual_dandelion"], "mapPin71610004": ["virtual_dandelion", "virtual_dandelion"], "mapPin71411635": ["virtual_black", "virtual_black"], "mapPin69853107": ["virtual_black", "virtual_black"], "mapPin71340713": ["virtual_black", "virtual_black"], "mapPin71419299": ["virtual_dandelion", "virtual_dandelion"], "mapPin69863388": ["virtual_dandelion", "virtual_dandelion"], "mapPin71340714": ["virtual_black", "virtual_black"], "mapPin71423236": ["virtual_black", "virtual_black"], "mapPin70918138": ["crossbow", "crossbow"], "mapPin71340728": ["virtual_dandelion", "virtual_dandelion"], "mapPin71621567": ["virtual_scarlet", "virtual_scarlet"], "mapPin71179724": ["virtual_black", "virtual_black"], "mapPin71473836": ["carnationseed", "yellowcarnationblossom"], "mapPin65900432": ["carnationseed", "violetcarnationblossom"], "mapPin71455268": ["carnationseed", "carnationbud"], "mapPin71340715": ["virtual_red", "virtual_red"], "mapPin71616322": ["virtual_dandelion", "virtual_dandelion"], "mapPin71636525": ["virtual_dandelion", "virtual_dandelion"], "mapPin71340696": ["virtual_black", "virtual_black"], "mapPin69855409": ["virtual_dandelion", "virtual_dandelion"], "mapPin71340695": ["virtual_dandelion", "virtual_dandelion"], "mapPin70603769": ["virtual_dandelion", "virtual_dandelion"], "mapPin71982389": ["virtual_black", "virtual_black"], "mapPin71340712": ["virtual_black", "virtual_black"], "mapPin42651578": ["crossbow", "crossbow"], "mapPin71350525": ["crossbow", "crossbow"], "mapPin69312090": ["crossbow", "crossbow"], "mapPin71328266": ["field", "field"], "mapPin51427649": ["virtual_brick_red", "virtual_red"], "mapPin71441136": ["virtual_red", "virtual_red"], "mapPin70506074": ["carnationseed", "carnationseed"], "mapPin36372660": ["virtual_red", "virtual_red"], "mapPin71328264": ["field", "field"], "mapPin70602518": ["virtual_dandelion", "virtual_dandelion"], "mapPin71308627": ["crossbow", "crossbow"], "mapPin70597872": ["crossbow", "crossbow"], "mapPin142663963": ["virtual_black", "virtual_black"], "mapPin71195312": ["virtual_dandelion", "virtual_dandelion"], "mapPin71465950": ["virtual_dandelion", "virtual_dandelion"], "mapPin71154161": ["virtual_black", "virtual_black"], "mapPin70122329": ["crossbow", "crossbow"], "mapPin70156808": ["crossbow", "crossbow"], "mapPin71424599": ["crossbow", "crossbow"], "mapPin71612687": ["crossbow", "crossbow"], "mapPin71227926": ["field", "field"], "mapPin71154994": ["virtual_red", "virtual_red"], "mapPin71394064": ["virtual_red", "virtual_red"], "mapPin71394121": ["virtual_red", "virtual_red"], "mapPin50455783": ["field", "field"], "mapPin69377700": ["crossbow", "crossbow"], "mapPin70404251": ["crossbow", "crossbow"], "mapPin71982398": ["crossbow", "crossbow"], "mapPin69377701": ["crossbow", "crossbow"], "mapPin71614274": ["crossbow", "crossbow"], "mapPin72090972": ["crossbow", "crossbow"], "mapPin70918796": ["crossbow", "crossbow"], "mapPin70918133": ["field", "pottedplant"], "mapPin71617931": ["virtual_red", "virtual_red"], "mapPin71473732": ["field", "garden"], "mapPin47840992": ["crossbow", "crossbow"], "mapPin71612570": ["crossbow", "crossbow"], "mapPin50136868": ["crossbow", "crossbow"], "mapPin69379271": ["crossbow", "crossbow"], "mapPin65774587": ["field", "pottedplant"], "mapPin71611327": ["crossbow", "crossbow"], "mapPin71613831": ["crossbow", "crossbow"], "mapPin70342006": ["crossbow", "crossbow"], "mapPin70849517": ["crossbow", "crossbow"]}, "unknow": {}, "corrected": {}, "undeployed": {}, "archived": {}, "insheet": {}, "freetype": {}, "gardens": {"Australia_LaidleyBeeLove": ""}}