{"deployed": {"mapPin21356207": ["virtual", "virtual"], "mapPin20180928": ["virtual", "virtual"], "mapPin20763516": ["virtual", "virtual"], "mapPin21463853": ["virtual", "virtual"], "mapPin21246745": ["virtual_red", "virtual_red"], "mapPin21466966": ["virtual", "virtual"], "mapPin21409178": ["virtual", "virtual"], "mapPin21518862": ["virtual_red", "virtual_red"], "mapPin21461096": ["virtual_red", "virtual_red"], "mapPin21524452": ["virtual_orange", "virtual_orange"], "mapPin21001254": ["virtual", "virtual"], "mapPin20180618": ["virtual", "virtual"], "mapPin21409481": ["virtual", "virtual"], "mapPin21400593": ["virtual_red", "virtual_red"], "mapPin21476735": ["virtual_red", "virtual_red"], "mapPin21355961": ["virtual_orange", "virtual_orange"], "mapPin21513814": ["virtual_red", "virtual_red"], "mapPin21326867": ["virtual_red", "virtual_red"], "mapPin21291073": ["virtual_red", "virtual_red"], "mapPin21393113": ["virtual", "virtual"], "mapPin21409186": ["virtual", "virtual"], "mapPin21559474": ["virtual_red", "virtual_red"], "mapPin21326866": ["virtual_red", "virtual_red"], "mapPin21519490": ["virtual_yellow", "virtual_yellow"], "mapPin34416555": ["virtual_yellow", "virtual_yellow"], "mapPin21529772": ["virtual_red", "virtual_red"], "mapPin21290151": ["virtual_red", "virtual_red"], "mapPin21001255": ["virtual", "virtual"], "mapPin21116683": ["virtual", "virtual"], "mapPin21120514": ["virtual_orange", "virtual_orange"], "mapPin21569711": ["virtual_orange", "virtual_orange"], "mapPin21127861": ["virtual_yellow", "virtual_yellow"], "mapPin21405206": ["virtual_yellow", "virtual_yellow"], "mapPin21289137": ["virtual_yellow", "virtual_yellow"], "mapPin21569714": ["virtual_orange", "virtual_orange"], "mapPin21255200": ["virtual", "virtual"], "mapPin21116678": ["virtual", "virtual"], "mapPin21569703": ["virtual_red", "virtual_red"], "mapPin21287501": ["virtual", "virtual"], "mapPin21586326": ["virtual", "virtual"], "mapPin21409172": ["virtual", "virtual"], "mapPin21485401": ["virtual_red", "virtual_red"], "mapPin21575765": ["virtual_red", "virtual_red"], "mapPin21355960": ["virtual_orange", "virtual_orange"], "mapPin21569712": ["virtual_red", "virtual_red"], "mapPin21559473": ["virtual_orange", "virtual_orange"], "mapPin21566408": ["virtual_red", "virtual_red"], "mapPin21443443": ["virtual_red", "virtual_red"], "mapPin21392409": ["virtual", "virtual"], "mapPin21258560": ["virtual", "virtual"], "mapPin21441665": ["virtual", "virtual"], "mapPin21461828": ["virtual", "virtual"], "mapPin21529511": ["virtual", "virtual"], "mapPin21482941": ["virtual", "virtual"], "mapPin34416673": ["virtual_orange", "virtual_orange"], "mapPin21569697": ["virtual_red", "virtual_red"], "mapPin21264672": ["virtual_orange", "virtual_orange"], "mapPin21108606": ["virtual_green", "virtual_green"], "mapPin21095632": ["virtual_green", "virtual_green"], "mapPin21409482": ["virtual_green", "virtual_green"], "mapPin21369097": ["virtual", "virtual"], "mapPin21112375": ["virtual", "virtual"], "mapPin21409184": ["virtual", "virtual"], "mapPin21524451": ["virtual_red", "virtual_red"], "mapPin21488805": ["virtual", "virtual"], "mapPin21441667": ["virtual", "virtual"], "mapPin21258555": ["virtual_green", "virtual_green"], "mapPin21513818": ["virtual_green", "virtual_green"], "mapPin21488376": ["virtual_green", "virtual_green"], "mapPin36334066": ["virtual", "virtual"], "mapPin21379940": ["virtual", "virtual"], "mapPin21513804": ["virtual", "virtual"], "mapPin20852058": ["virtual_green", "virtual_green"], "mapPin21569698": ["virtual_green", "virtual_green"], "mapPin21569710": ["virtual_green", "virtual_green"], "mapPin20695168": ["virtual", "virtual"], "mapPin21165705": ["virtual_green", "virtual_green"], "mapPin21569704": ["virtual_green", "virtual_green"], "mapPin21488798": ["virtual", "virtual"], "mapPin21524190": ["virtual_green", "virtual_green"], "mapPin21326868": ["virtual", "virtual"], "mapPin37043929": ["virtual_forest_green", "virtual_green"], "mapPin21524459": ["virtual", "virtual"], "mapPin21488804": ["virtual", "virtual"], "mapPin21417785": ["virtual", "virtual"], "mapPin21441669": ["virtual", "virtual"], "mapPin20936612": ["virtual", "virtual"], "mapPin21441668": ["virtual", "virtual"], "mapPin21409185": ["virtual", "virtual"], "mapPin123598797": ["virtual", ""], "mapPin218847476": ["virtual_orange", ""], "mapPin214740541": ["virtual_red", ""], "mapPin50122028": ["poivirtualgarden", "poivirtualgarden"], "mapPin20565525": ["virtual_red", "virtual_red"]}, "unknow": {"unknow1695358026.023986": ["", "47.7504839955866", "18.099645542907638", "virtual_red"]}, "corrected": {"mapPin37043929": ["virtual_forest_green", "virtual_green", "maagika/271/"]}, "undeployed": {}, "archived": {"archived21255240": ["lbruggeman/1313/", "47.751150929064664", "18.09880482704989", "virtual"], "archived19488505": ["gonczi/641/", "47.751113728702826", "18.099011315411417", "virtual_orange"], "archived21488803": ["minikaloz/215/", "47.75090049501659", "18.099479605026772", "virtual_orange"], "archived21289144": ["icehalm/251/", "47.75062282882032", "18.09959023063459", "virtual_orange"], "archived21258562": ["icehalm/249/", "47.750669997395725", "18.09861311211705", "virtual_red"], "archived19477888": ["gonczi/639/", "47.75059559667207", "18.099026084876073", "virtual_yellow"], "archived21079982": ["vivszi/141/", "47.75055839631024", "18.099232571034236", "virtual_yellow"], "archived21537565": ["frf/3154/", "47.75052119594842", "18.09943905704472", "virtual_red"], "archived21409179": ["kiskaloz/196/", "47.7502063293903", "18.099756166096768", "virtual"], "archived21409182": ["minikaloz/213/", "47.75016912902848", "18.09996265071038", "virtual"], "archived21116685": ["icehalm/237/", "47.75006749642776", "18.09981147701319", "virtual"], "archived21537564": ["frf/3153/", "47.75000306391773", "18.099453820206463", "virtual_green"], "archived21310420": ["frf/2957/", "47.749891462832274", "18.10007327118535", "virtual_green"], "archived21500300": ["liteon163/459/", "47.74997583204061", "18.098889680763477", "virtual"], "archived21500301": ["liteon163/460/", "47.74982703059333", "18.09971561467455", "virtual"], "archived21488802": ["kiskaloz/200/", "47.74978983023151", "18.099922097783292", "virtual"], "archived21476241": ["kiskaloz/199/", "47.74983699880691", "18.098944993372243", "virtual"], "archived21112377": ["icehalm/236/", "47.749613796636", "18.10018389004847", "virtual_green"]}, "insheet": {}, "freetype": {}}