{"deployed": {"mapPin38353741": ["flatrob", ["flatlou", "flatmatt", "flatrob", "flathammock", "flatdhs", "flatdiscgolfbasket", "flatflashlight", "flatcats", "flatmurray", "flattypewriter", "flatvan", "flatrum"]], "mapPin70692564": ["flatlou", ["flatlou", "flatmatt", "flatrob", "flathammock", "flatdhs", "flatdiscgolfbasket", "flatflashlight", "flatcats", "flatmurray", "flattypewriter", "flatvan", "flatrum"]], "mapPin72705189": ["flathammock", ["flatlou", "flatmatt", "flatrob", "flathammock", "flatdhs", "flatdiscgolfbasket", "flatflashlight", "flatcats", "flatmurray", "flattypewriter", "flatvan", "flatrum"]], "mapPin70484290": ["flathammock", ["flatlou", "flatmatt", "flatrob", "flathammock", "flatdhs", "flatdiscgolfbasket", "flatflashlight", "flatcats", "flatmurray", "flattypewriter", "flatvan", "flatrum"]], "mapPin82628605": ["flatlou", ["flatlou", "flatmatt", "flatrob", "flathammock", "flatdhs", "flatdiscgolfbasket", "flatflashlight", "flatcats", "flatmurray", "flattypewriter", "flatvan", "flatrum"]], "mapPin72280576": ["flathammock", ["flatlou", "flatmatt", "flatrob", "flathammock", "flatdhs", "flatdiscgolfbasket", "flatflashlight", "flatcats", "flatmurray", "flattypewriter", "flatvan", "flatrum"]], "mapPin73595769": ["flathammock", ["flatlou", "flatmatt", "flatrob", "flathammock", "flatdhs", "flatdiscgolfbasket", "flatflashlight", "flatcats", "flatmurray", "flattypewriter", "flatvan", "flatrum"]], "mapPin79757637": ["flathammock", ["flatlou", "flatmatt", "flatrob", "flathammock", "flatdhs", "flatdiscgolfbasket", "flatflashlight", "flatcats", "flatmurray", "flattypewriter", "flatvan", "flatrum"]], "mapPin72334534": ["flatlou", ["flatlou", "flatmatt", "flatrob", "flathammock", "flatdhs", "flatdiscgolfbasket", "flatflashlight", "flatcats", "flatmurray", "flattypewriter", "flatvan", "flatrum"]], "mapPin73497934": ["flathammock", ["flatlou", "flatmatt", "flatrob", "flathammock", "flatdhs", "flatdiscgolfbasket", "flatflashlight", "flatcats", "flatmurray", "flattypewriter", "flatvan", "flatrum"]], "mapPin73429090": ["flatrob", ["flatlou", "flatmatt", "flatrob", "flathammock", "flatdhs", "flatdiscgolfbasket", "flatflashlight", "flatcats", "flatmurray", "flattypewriter", "flatvan", "flatrum"]], "mapPin72034403": ["flathammock", ["flatlou", "flatmatt", "flatrob", "flathammock", "flatdhs", "flatdiscgolfbasket", "flatflashlight", "flatcats", "flatmurray", "flattypewriter", "flatvan", "flatrum"]], "mapPin45758612": ["flatmatt", ["flatlou", "flatmatt", "flatrob", "flathammock", "flatdhs", "flatdiscgolfbasket", "flatflashlight", "flatcats", "flatmurray", "flattypewriter", "flatvan", "flatrum"]], "mapPin71086611": ["flatlou", ["flatlou", "flatmatt", "flatrob", "flathammock", "flatdhs", "flatdiscgolfbasket", "flatflashlight", "flatcats", "flatmurray", "flattypewriter", "flatvan", "flatrum"]], "mapPin72077335": ["flathammock", ["flatlou", "flatmatt", "flatrob", "flathammock", "flatdhs", "flatdiscgolfbasket", "flatflashlight", "flatcats", "flatmurray", "flattypewriter", "flatvan", "flatrum"]], "mapPin71321321": ["flatmatt", ["flatlou", "flatmatt", "flatrob", "flathammock", "flatdhs", "flatdiscgolfbasket", "flatflashlight", "flatcats", "flatmurray", "flattypewriter", "flatvan", "flatrum"]], "mapPin76484465": ["flatlou", ["flatlou", "flatmatt", "flatrob", "flathammock", "flatdhs", "flatdiscgolfbasket", "flatflashlight", "flatcats", "flatmurray", "flattypewriter", "flatvan", "flatrum"]], "mapPin72334535": ["flathammock", ["flatlou", "flatmatt", "flatrob", "flathammock", "flatdhs", "flatdiscgolfbasket", "flatflashlight", "flatcats", "flatmurray", "flattypewriter", "flatvan", "flatrum"]], "mapPin73430030": ["flathammock", ["flatlou", "flatmatt", "flatrob", "flathammock", "flatdhs", "flatdiscgolfbasket", "flatflashlight", "flatcats", "flatmurray", "flattypewriter", "flatvan", "flatrum"]], "mapPin77611911": ["flatlou", ["flatlou", "flatmatt", "flatrob", "flathammock", "flatdhs", "flatdiscgolfbasket", "flatflashlight", "flatcats", "flatmurray", "flattypewriter", "flatvan", "flatrum"]], "mapPin72331416": ["flathammock", ["flatlou", "flatmatt", "flatrob", "flathammock", "flatdhs", "flatdiscgolfbasket", "flatflashlight", "flatcats", "flatmurray", "flattypewriter", "flatvan", "flatrum"]], "mapPin72331285": ["flathammock", ["flatlou", "flatmatt", "flatrob", "flathammock", "flatdhs", "flatdiscgolfbasket", "flatflashlight", "flatcats", "flatmurray", "flattypewriter", "flatvan", "flatrum"]], "mapPin70909897": ["flatlou", ["flatlou", "flatmatt", "flatrob", "flathammock", "flatdhs", "flatdiscgolfbasket", "flatflashlight", "flatcats", "flatmurray", "flattypewriter", "flatvan", "flatrum"]], "mapPin76634299": ["flatlou", ["flatlou", "flatmatt", "flatrob", "flathammock", "flatdhs", "flatdiscgolfbasket", "flatflashlight", "flatcats", "flatmurray", "flattypewriter", "flatvan", "flatrum"]], "mapPin73459041": ["flatlou", ["flatlou", "flatmatt", "flatrob", "flathammock", "flatdhs", "flatdiscgolfbasket", "flatflashlight", "flatcats", "flatmurray", "flattypewriter", "flatvan", "flatrum"]], "mapPin70909898": ["flatlou", ["flatlou", "flatmatt", "flatrob", "flathammock", "flatdhs", "flatdiscgolfbasket", "flatflashlight", "flatcats", "flatmurray", "flattypewriter", "flatvan", "flatrum"]], "mapPin76491349": ["flatlou", ["flatlou", "flatmatt", "flatrob", "flathammock", "flatdhs", "flatdiscgolfbasket", "flatflashlight", "flatcats", "flatmurray", "flattypewriter", "flatvan", "flatrum"]], "mapPin82641564": ["flatlou", ["flatlou", "flatmatt", "flatrob", "flathammock", "flatdhs", "flatdiscgolfbasket", "flatflashlight", "flatcats", "flatmurray", "flattypewriter", "flatvan", "flatrum"]], "mapPin73724853": ["flatlou", ["flatlou", "flatmatt", "flatrob", "flathammock", "flatdhs", "flatdiscgolfbasket", "flatflashlight", "flatcats", "flatmurray", "flattypewriter", "flatvan", "flatrum"]], "mapPin70851635": ["flathammock", ["flatlou", "flatmatt", "flatrob", "flathammock", "flatdhs", "flatdiscgolfbasket", "flatflashlight", "flatcats", "flatmurray", "flattypewriter", "flatvan", "flatrum"]], "mapPin65567242": ["flathammock", ["flatlou", "flatmatt", "flatrob", "flathammock", "flatdhs", "flatdiscgolfbasket", "flatflashlight", "flatcats", "flatmurray", "flattypewriter", "flatvan", "flatrum"]], "mapPin73421129": ["flatlou", ["flatlou", "flatmatt", "flatrob", "flathammock", "flatdhs", "flatdiscgolfbasket", "flatflashlight", "flatcats", "flatmurray", "flattypewriter", "flatvan", "flatrum"]], "mapPin71086620": ["flathammock", ["flatlou", "flatmatt", "flatrob", "flathammock", "flatdhs", "flatdiscgolfbasket", "flatflashlight", "flatcats", "flatmurray", "flattypewriter", "flatvan", "flatrum"]], "mapPin71086637": ["flathammock", ["flatlou", "flatmatt", "flatrob", "flathammock", "flatdhs", "flatdiscgolfbasket", "flatflashlight", "flatcats", "flatmurray", "flattypewriter", "flatvan", "flatrum"]], "mapPin69365236": ["flatlou", ["flatlou", "flatmatt", "flatrob", "flathammock", "flatdhs", "flatdiscgolfbasket", "flatflashlight", "flatcats", "flatmurray", "flattypewriter", "flatvan", "flatrum"]], "mapPin79757855": ["flatlou", ["flatlou", "flatmatt", "flatrob", "flathammock", "flatdhs", "flatdiscgolfbasket", "flatflashlight", "flatcats", "flatmurray", "flattypewriter", "flatvan", "flatrum"]], "mapPin82206128": ["flatlou", ["flatlou", "flatmatt", "flatrob", "flathammock", "flatdhs", "flatdiscgolfbasket", "flatflashlight", "flatcats", "flatmurray", "flattypewriter", "flatvan", "flatrum"]], "mapPin70909899": ["flatlou", ["flatlou", "flatmatt", "flatrob", "flathammock", "flatdhs", "flatdiscgolfbasket", "flatflashlight", "flatcats", "flatmurray", "flattypewriter", "flatvan", "flatrum"]], "mapPin73145608": ["flatlou", ["flatlou", "flatmatt", "flatrob", "flathammock", "flatdhs", "flatdiscgolfbasket", "flatflashlight", "flatcats", "flatmurray", "flattypewriter", "flatvan", "flatrum"]], "mapPin73145592": ["flatlou", ["flatlou", "flatmatt", "flatrob", "flathammock", "flatdhs", "flatdiscgolfbasket", "flatflashlight", "flatcats", "flatmurray", "flattypewriter", "flatvan", "flatrum"]], "mapPin79086927": ["flatlou", ["flatlou", "flatmatt", "flatrob", "flathammock", "flatdhs", "flatdiscgolfbasket", "flatflashlight", "flatcats", "flatmurray", "flattypewriter", "flatvan", "flatrum"]], "mapPin71640878": ["flatlou", ["flatlou", "flatmatt", "flatrob", "flathammock", "flatdhs", "flatdiscgolfbasket", "flatflashlight", "flatcats", "flatmurray", "flattypewriter", "flatvan", "flatrum"]], "mapPin71216944": ["flatlou", ["flatlou", "flatmatt", "flatrob", "flathammock", "flatdhs", "flatdiscgolfbasket", "flatflashlight", "flatcats", "flatmurray", "flattypewriter", "flatvan", "flatrum"]], "mapPin79595373": ["flathammock", ["flatlou", "flatmatt", "flatrob", "flathammock", "flatdhs", "flatdiscgolfbasket", "flatflashlight", "flatcats", "flatmurray", "flattypewriter", "flatvan", "flatrum"]], "mapPin71161789": ["flatlou", ["flatlou", "flatmatt", "flatrob", "flathammock", "flatdhs", "flatdiscgolfbasket", "flatflashlight", "flatcats", "flatmurray", "flattypewriter", "flatvan", "flatrum"]], "mapPin121991304": ["flatlou", ["flatlou", "flatmatt", "flatrob", "flathammock", "flatdhs", "flatdiscgolfbasket", "flatflashlight", "flatcats", "flatmurray", "flattypewriter", "flatvan", "flatrum"]], "mapPin70691612": ["flatlou", ["flatlou", "flatmatt", "flatrob", "flathammock", "flatdhs", "flatdiscgolfbasket", "flatflashlight", "flatcats", "flatmurray", "flattypewriter", "flatvan", "flatrum"]], "mapPin73423227": ["flathammock", ["flatlou", "flatmatt", "flatrob", "flathammock", "flatdhs", "flatdiscgolfbasket", "flatflashlight", "flatcats", "flatmurray", "flattypewriter", "flatvan", "flatrum"]], "mapPin121989084": ["flatlou", ["flatlou", "flatmatt", "flatrob", "flathammock", "flatdhs", "flatdiscgolfbasket", "flatflashlight", "flatcats", "flatmurray", "flattypewriter", "flatvan", "flatrum"]], "mapPin73459042": ["flathammock", ["flatlou", "flatmatt", "flatrob", "flathammock", "flatdhs", "flatdiscgolfbasket", "flatflashlight", "flatcats", "flatmurray", "flattypewriter", "flatvan", "flatrum"]], "mapPin142505088": ["flatrob", ["flatlou", "flatmatt", "flatrob", "flathammock", "flatdhs", "flatdiscgolfbasket", "flatflashlight", "flatcats", "flatmurray", "flattypewriter", "flatvan", "flatrum"]], "mapPin73459056": ["flathammock", ["flatlou", "flatmatt", "flatrob", "flathammock", "flatdhs", "flatdiscgolfbasket", "flatflashlight", "flatcats", "flatmurray", "flattypewriter", "flatvan", "flatrum"]], "mapPin73459057": ["flathammock", ["flatlou", "flatmatt", "flatrob", "flathammock", "flatdhs", "flatdiscgolfbasket", "flatflashlight", "flatcats", "flatmurray", "flattypewriter", "flatvan", "flatrum"]], "mapPin95422229": ["flatrob", ["flatlou", "flatmatt", "flatrob", "flathammock", "flatdhs", "flatdiscgolfbasket", "flatflashlight", "flatcats", "flatmurray", "flattypewriter", "flatvan", "flatrum"]], "mapPin85058774": ["flathammock", ["flatlou", "flatmatt", "flatrob", "flathammock", "flatdhs", "flatdiscgolfbasket", "flatflashlight", "flatcats", "flatmurray", "flattypewriter", "flatvan", "flatrum"]], "mapPin73544861": ["flatlou", ["flatlou", "flatmatt", "flatrob", "flathammock", "flatdhs", "flatdiscgolfbasket", "flatflashlight", "flatcats", "flatmurray", "flattypewriter", "flatvan", "flatrum"]], "mapPin93492256": ["flatrob", ["flatlou", "flatmatt", "flatrob", "flathammock", "flatdhs", "flatdiscgolfbasket", "flatflashlight", "flatcats", "flatmurray", "flattypewriter", "flatvan", "flatrum"]], "mapPin92270937": ["flatrob", ["flatlou", "flatmatt", "flatrob", "flathammock", "flatdhs", "flatdiscgolfbasket", "flatflashlight", "flatcats", "flatmurray", "flattypewriter", "flatvan", "flatrum"]], "mapPin79759597": ["flatrob", ["flatlou", "flatmatt", "flatrob", "flathammock", "flatdhs", "flatdiscgolfbasket", "flatflashlight", "flatcats", "flatmurray", "flattypewriter", "flatvan", "flatrum"]], "mapPin95422239": ["flatlou", ["flatlou", "flatmatt", "flatrob", "flathammock", "flatdhs", "flatdiscgolfbasket", "flatflashlight", "flatcats", "flatmurray", "flattypewriter", "flatvan", "flatrum"]], "mapPin93492337": ["flatlou", ["flatlou", "flatmatt", "flatrob", "flathammock", "flatdhs", "flatdiscgolfbasket", "flatflashlight", "flatcats", "flatmurray", "flattypewriter", "flatvan", "flatrum"]], "mapPin80400415": ["flatmatt", ["flatlou", "flatmatt", "flatrob", "flathammock", "flatdhs", "flatdiscgolfbasket", "flatflashlight", "flatcats", "flatmurray", "flattypewriter", "flatvan", "flatrum"]], "mapPin80390229": ["flathammock", ["flatlou", "flatmatt", "flatrob", "flathammock", "flatdhs", "flatdiscgolfbasket", "flatflashlight", "flatcats", "flatmurray", "flattypewriter", "flatvan", "flatrum"]], "mapPin79767361": ["flathammock", ["flatlou", "flatmatt", "flatrob", "flathammock", "flatdhs", "flatdiscgolfbasket", "flatflashlight", "flatcats", "flatmurray", "flattypewriter", "flatvan", "flatrum"]], "mapPin132871113": ["flatrob", ["flatlou", "flatmatt", "flatrob", "flathammock", "flatdhs", "flatdiscgolfbasket", "flatflashlight", "flatcats", "flatmurray", "flattypewriter", "flatvan", "flatrum"]], "mapPin71326372": ["flatrob", ["flatlou", "flatmatt", "flatrob", "flathammock", "flatdhs", "flatdiscgolfbasket", "flatflashlight", "flatcats", "flatmurray", "flattypewriter", "flatvan", "flatrum"]], "mapPin155448480": ["flatlou", ["flatlou", "flatmatt", "flatrob", "flathammock", "flatdhs", "flatdiscgolfbasket", "flatflashlight", "flatcats", "flatmurray", "flattypewriter", "flatvan", "flatrum"]], "mapPin72712904": ["flathammock", ["flatlou", "flatmatt", "flatrob", "flathammock", "flatdhs", "flatdiscgolfbasket", "flatflashlight", "flatcats", "flatmurray", "flattypewriter", "flatvan", "flatrum"]], "mapPin158284993": ["flatlou", ["flatlou", "flatmatt", "flatrob", "flathammock", "flatdhs", "flatdiscgolfbasket", "flatflashlight", "flatcats", "flatmurray", "flattypewriter", "flatvan", "flatrum"]], "mapPin71307476": ["flatrob", ["flatlou", "flatmatt", "flatrob", "flathammock", "flatdhs", "flatdiscgolfbasket", "flatflashlight", "flatcats", "flatmurray", "flattypewriter", "flatvan", "flatrum"]], "mapPin73459058": ["flathammock", ["flatlou", "flatmatt", "flatrob", "flathammock", "flatdhs", "flatdiscgolfbasket", "flatflashlight", "flatcats", "flatmurray", "flattypewriter", "flatvan", "flatrum"]], "mapPin47302026": ["flatrob", ["flatlou", "flatmatt", "flatrob", "flathammock", "flatdhs", "flatdiscgolfbasket", "flatflashlight", "flatcats", "flatmurray", "flattypewriter", "flatvan", "flatrum"]], "mapPin73459059": ["flathammock", ["flatlou", "flatmatt", "flatrob", "flathammock", "flatdhs", "flatdiscgolfbasket", "flatflashlight", "flatcats", "flatmurray", "flattypewriter", "flatvan", "flatrum"]], "mapPin73459062": ["flathammock", ["flatlou", "flatmatt", "flatrob", "flathammock", "flatdhs", "flatdiscgolfbasket", "flatflashlight", "flatcats", "flatmurray", "flattypewriter", "flatvan", "flatrum"]], "mapPin136434316": ["flatlou", ["flatlou", "flatmatt", "flatrob", "flathammock", "flatdhs", "flatdiscgolfbasket", "flatflashlight", "flatcats", "flatmurray", "flattypewriter", "flatvan", "flatrum"]], "mapPin73459064": ["flathammock", ["flatlou", "flatmatt", "flatrob", "flathammock", "flatdhs", "flatdiscgolfbasket", "flatflashlight", "flatcats", "flatmurray", "flattypewriter", "flatvan", "flatrum"]], "mapPin132340009": ["flatlou", ["flatlou", "flatmatt", "flatrob", "flathammock", "flatdhs", "flatdiscgolfbasket", "flatflashlight", "flatcats", "flatmurray", "flattypewriter", "flatvan", "flatrum"]], "mapPin73459066": ["flathammock", ["flatlou", "flatmatt", "flatrob", "flathammock", "flatdhs", "flatdiscgolfbasket", "flatflashlight", "flatcats", "flatmurray", "flattypewriter", "flatvan", "flatrum"]], "mapPin73459067": ["flathammock", ["flatlou", "flatmatt", "flatrob", "flathammock", "flatdhs", "flatdiscgolfbasket", "flatflashlight", "flatcats", "flatmurray", "flattypewriter", "flatvan", "flatrum"]], "mapPin36253424": ["flatrob", ["flatlou", "flatmatt", "flatrob", "flathammock", "flatdhs", "flatdiscgolfbasket", "flatflashlight", "flatcats", "flatmurray", "flattypewriter", "flatvan", "flatrum"]], "mapPin73585931": ["flatmatt", ["flatlou", "flatmatt", "flatrob", "flathammock", "flatdhs", "flatdiscgolfbasket", "flatflashlight", "flatcats", "flatmurray", "flattypewriter", "flatvan", "flatrum"]], "mapPin153193115": ["flatlou", ["flatlou", "flatmatt", "flatrob", "flathammock", "flatdhs", "flatdiscgolfbasket", "flatflashlight", "flatcats", "flatmurray", "flattypewriter", "flatvan", "flatrum"]], "mapPin170456095": ["flatlou", ["flatlou", "flatmatt", "flatrob", "flathammock", "flatdhs", "flatdiscgolfbasket", "flatflashlight", "flatcats", "flatmurray", "flattypewriter", "flatvan", "flatrum"]], "mapPin138889473": ["flatlou", ["flatlou", "flatmatt", "flatrob", "flathammock", "flatdhs", "flatdiscgolfbasket", "flatflashlight", "flatcats", "flatmurray", "flattypewriter", "flatvan", "flatrum"]], "mapPin82197583": ["flatlou", ["flatlou", "flatmatt", "flatrob", "flathammock", "flatdhs", "flatdiscgolfbasket", "flatflashlight", "flatcats", "flatmurray", "flattypewriter", "flatvan", "flatrum"]], "mapPin170455929": ["flatrob", ["flatlou", "flatmatt", "flatrob", "flathammock", "flatdhs", "flatdiscgolfbasket", "flatflashlight", "flatcats", "flatmurray", "flattypewriter", "flatvan", "flatrum"]], "mapPin187862418": ["flatdiscgolfbasket", ["flatlou", "flatmatt", "flatrob", "flathammock", "flatdhs", "flatdiscgolfbasket", "flatflashlight", "flatcats", "flatmurray", "flattypewriter", "flatvan", "flatrum"]], "mapPin115150450": ["flatrob", ["flatlou", "flatmatt", "flatrob", "flathammock", "flatdhs", "flatdiscgolfbasket", "flatflashlight", "flatcats", "flatmurray", "flattypewriter", "flatvan", "flatrum"]], "mapPin170460540": ["flatlou", ["flatlou", "flatmatt", "flatrob", "flathammock", "flatdhs", "flatdiscgolfbasket", "flatflashlight", "flatcats", "flatmurray", "flattypewriter", "flatvan", "flatrum"]], "mapPin73459068": ["flathammock", ["flatlou", "flatmatt", "flatrob", "flathammock", "flatdhs", "flatdiscgolfbasket", "flatflashlight", "flatcats", "flatmurray", "flattypewriter", "flatvan", "flatrum"]], "mapPin73459072": ["flathammock", ["flatlou", "flatmatt", "flatrob", "flathammock", "flatdhs", "flatdiscgolfbasket", "flatflashlight", "flatcats", "flatmurray", "flattypewriter", "flatvan", "flatrum"]], "mapPin73459078": ["flathammock", ["flatlou", "flatmatt", "flatrob", "flathammock", "flatdhs", "flatdiscgolfbasket", "flatflashlight", "flatcats", "flatmurray", "flattypewriter", "flatvan", "flatrum"]], "mapPin80614114": ["flatrob", ["flatlou", "flatmatt", "flatrob", "flathammock", "flatdhs", "flatdiscgolfbasket", "flatflashlight", "flatcats", "flatmurray", "flattypewriter", "flatvan", "flatrum"]], "mapPin73459084": ["flathammock", ["flatlou", "flatmatt", "flatrob", "flathammock", "flatdhs", "flatdiscgolfbasket", "flatflashlight", "flatcats", "flatmurray", "flattypewriter", "flatvan", "flatrum"]], "mapPin187761302": ["flatdiscgolfbasket", ["flatlou", "flatmatt", "flatrob", "flathammock", "flatdhs", "flatdiscgolfbasket", "flatflashlight", "flatcats", "flatmurray", "flattypewriter", "flatvan", "flatrum"]], "mapPin183363939": ["flatdhs", ["flatlou", "flatmatt", "flatrob", "flathammock", "flatdhs", "flatdiscgolfbasket", "flatflashlight", "flatcats", "flatmurray", "flattypewriter", "flatvan", "flatrum"]], "mapPin152488895": ["flatrob", ["flatlou", "flatmatt", "flatrob", "flathammock", "flatdhs", "flatdiscgolfbasket", "flatflashlight", "flatcats", "flatmurray", "flattypewriter", "flatvan", "flatrum"]], "mapPin187790019": ["flatdiscgolfbasket", ["flatlou", "flatmatt", "flatrob", "flathammock", "flatdhs", "flatdiscgolfbasket", "flatflashlight", "flatcats", "flatmurray", "flattypewriter", "flatvan", "flatrum"]], "mapPin186486946": ["flatdiscgolfbasket", ["flatlou", "flatmatt", "flatrob", "flathammock", "flatdhs", "flatdiscgolfbasket", "flatflashlight", "flatcats", "flatmurray", "flattypewriter", "flatvan", "flatrum"]], "mapPin186485060": ["flatdiscgolfbasket", ["flatlou", "flatmatt", "flatrob", "flathammock", "flatdhs", "flatdiscgolfbasket", "flatflashlight", "flatcats", "flatmurray", "flattypewriter", "flatvan", "flatrum"]], "mapPin186467100": ["flatdiscgolfbasket", ["flatlou", "flatmatt", "flatrob", "flathammock", "flatdhs", "flatdiscgolfbasket", "flatflashlight", "flatcats", "flatmurray", "flattypewriter", "flatvan", "flatrum"]], "mapPin187634079": ["flatdiscgolfbasket", ["flatlou", "flatmatt", "flatrob", "flathammock", "flatdhs", "flatdiscgolfbasket", "flatflashlight", "flatcats", "flatmurray", "flattypewriter", "flatvan", "flatrum"]], "mapPin185152222": ["flatdiscgolfbasket", ["flatlou", "flatmatt", "flatrob", "flathammock", "flatdhs", "flatdiscgolfbasket", "flatflashlight", "flatcats", "flatmurray", "flattypewriter", "flatvan", "flatrum"]], "mapPin188456395": ["flatdiscgolfbasket", ["flatlou", "flatmatt", "flatrob", "flathammock", "flatdhs", "flatdiscgolfbasket", "flatflashlight", "flatcats", "flatmurray", "flattypewriter", "flatvan", "flatrum"]], "mapPin73459096": ["flathammock", ["flatlou", "flatmatt", "flatrob", "flathammock", "flatdhs", "flatdiscgolfbasket", "flatflashlight", "flatcats", "flatmurray", "flattypewriter", "flatvan", "flatrum"]], "mapPin186482627": ["flatdiscgolfbasket", ["flatlou", "flatmatt", "flatrob", "flathammock", "flatdhs", "flatdiscgolfbasket", "flatflashlight", "flatcats", "flatmurray", "flattypewriter", "flatvan", "flatrum"]], "mapPin73459097": ["flathammock", ["flatlou", "flatmatt", "flatrob", "flathammock", "flatdhs", "flatdiscgolfbasket", "flatflashlight", "flatcats", "flatmurray", "flattypewriter", "flatvan", "flatrum"]], "mapPin73459098": ["flathammock", ["flatlou", "flatmatt", "flatrob", "flathammock", "flatdhs", "flatdiscgolfbasket", "flatflashlight", "flatcats", "flatmurray", "flattypewriter", "flatvan", "flatrum"]], "mapPin186482991": ["flatdiscgolfbasket", ["flatlou", "flatmatt", "flatrob", "flathammock", "flatdhs", "flatdiscgolfbasket", "flatflashlight", "flatcats", "flatmurray", "flattypewriter", "flatvan", "flatrum"]], "mapPin185167539": ["flatdiscgolfbasket", ["flatlou", "flatmatt", "flatrob", "flathammock", "flatdhs", "flatdiscgolfbasket", "flatflashlight", "flatcats", "flatmurray", "flattypewriter", "flatvan", "flatrum"]], "mapPin186469607": ["flatdiscgolfbasket", ["flatlou", "flatmatt", "flatrob", "flathammock", "flatdhs", "flatdiscgolfbasket", "flatflashlight", "flatcats", "flatmurray", "flattypewriter", "flatvan", "flatrum"]], "mapPin186505759": ["flatdiscgolfbasket", ["flatlou", "flatmatt", "flatrob", "flathammock", "flatdhs", "flatdiscgolfbasket", "flatflashlight", "flatcats", "flatmurray", "flattypewriter", "flatvan", "flatrum"]], "mapPin185744253": ["flatdiscgolfbasket", ["flatlou", "flatmatt", "flatrob", "flathammock", "flatdhs", "flatdiscgolfbasket", "flatflashlight", "flatcats", "flatmurray", "flattypewriter", "flatvan", "flatrum"]], "mapPin125992768": ["flatlou", ["flatlou", "flatmatt", "flatrob", "flathammock", "flatdhs", "flatdiscgolfbasket", "flatflashlight", "flatcats", "flatmurray", "flattypewriter", "flatvan", "flatrum"]], "mapPin185698229": ["flatdiscgolfbasket", ["flatlou", "flatmatt", "flatrob", "flathammock", "flatdhs", "flatdiscgolfbasket", "flatflashlight", "flatcats", "flatmurray", "flattypewriter", "flatvan", "flatrum"]], "mapPin187706915": ["flatdiscgolfbasket", ["flatlou", "flatmatt", "flatrob", "flathammock", "flatdhs", "flatdiscgolfbasket", "flatflashlight", "flatcats", "flatmurray", "flattypewriter", "flatvan", "flatrum"]], "mapPin192711330": ["flatdhs", ["flatlou", "flatmatt", "flatrob", "flathammock", "flatdhs", "flatdiscgolfbasket", "flatflashlight", "flatcats", "flatmurray", "flattypewriter", "flatvan", "flatrum"]], "mapPin186572087": ["flatdiscgolfbasket", ["flatlou", "flatmatt", "flatrob", "flathammock", "flatdhs", "flatdiscgolfbasket", "flatflashlight", "flatcats", "flatmurray", "flattypewriter", "flatvan", "flatrum"]], "mapPin186485269": ["flatdiscgolfbasket", ["flatlou", "flatmatt", "flatrob", "flathammock", "flatdhs", "flatdiscgolfbasket", "flatflashlight", "flatcats", "flatmurray", "flattypewriter", "flatvan", "flatrum"]], "mapPin185854606": ["flatdiscgolfbasket", ["flatlou", "flatmatt", "flatrob", "flathammock", "flatdhs", "flatdiscgolfbasket", "flatflashlight", "flatcats", "flatmurray", "flattypewriter", "flatvan", "flatrum"]], "mapPin72056192": ["flatrob", ["flatlou", "flatmatt", "flatrob", "flathammock", "flatdhs", "flatdiscgolfbasket", "flatflashlight", "flatcats", "flatmurray", "flattypewriter", "flatvan", "flatrum"]], "mapPin73459106": ["flathammock", ["flatlou", "flatmatt", "flatrob", "flathammock", "flatdhs", "flatdiscgolfbasket", "flatflashlight", "flatcats", "flatmurray", "flattypewriter", "flatvan", "flatrum"]], "mapPin73459107": ["flathammock", ["flatlou", "flatmatt", "flatrob", "flathammock", "flatdhs", "flatdiscgolfbasket", "flatflashlight", "flatcats", "flatmurray", "flattypewriter", "flatvan", "flatrum"]], "mapPin194170650": ["flatdhs", ["flatlou", "flatmatt", "flatrob", "flathammock", "flatdhs", "flatdiscgolfbasket", "flatflashlight", "flatcats", "flatmurray", "flattypewriter", "flatvan", "flatrum"]], "mapPin73459109": ["flathammock", ["flatlou", "flatmatt", "flatrob", "flathammock", "flatdhs", "flatdiscgolfbasket", "flatflashlight", "flatcats", "flatmurray", "flattypewriter", "flatvan", "flatrum"]], "mapPin193916267": ["flatdhs", ["flatlou", "flatmatt", "flatrob", "flathammock", "flatdhs", "flatdiscgolfbasket", "flatflashlight", "flatcats", "flatmurray", "flattypewriter", "flatvan", "flatrum"]], "mapPin185636267": ["flatdiscgolfbasket", ["flatlou", "flatmatt", "flatrob", "flathammock", "flatdhs", "flatdiscgolfbasket", "flatflashlight", "flatcats", "flatmurray", "flattypewriter", "flatvan", "flatrum"]], "mapPin185350081": ["flatdiscgolfbasket", ["flatlou", "flatmatt", "flatrob", "flathammock", "flatdhs", "flatdiscgolfbasket", "flatflashlight", "flatcats", "flatmurray", "flattypewriter", "flatvan", "flatrum"]], "mapPin190233838": ["flatdhs", ["flatlou", "flatmatt", "flatrob", "flathammock", "flatdhs", "flatdiscgolfbasket", "flatflashlight", "flatcats", "flatmurray", "flattypewriter", "flatvan", "flatrum"]], "mapPin184945558": ["flatdiscgolfbasket", ["flatlou", "flatmatt", "flatrob", "flathammock", "flatdhs", "flatdiscgolfbasket", "flatflashlight", "flatcats", "flatmurray", "flattypewriter", "flatvan", "flatrum"]], "mapPin194464589": ["flatdhs", ["flatlou", "flatmatt", "flatrob", "flathammock", "flatdhs", "flatdiscgolfbasket", "flatflashlight", "flatcats", "flatmurray", "flattypewriter", "flatvan", "flatrum"]], "mapPin185676956": ["flatdiscgolfbasket", ["flatlou", "flatmatt", "flatrob", "flathammock", "flatdhs", "flatdiscgolfbasket", "flatflashlight", "flatcats", "flatmurray", "flattypewriter", "flatvan", "flatrum"]], "mapPin194464581": ["flatdhs", ["flatlou", "flatmatt", "flatrob", "flathammock", "flatdhs", "flatdiscgolfbasket", "flatflashlight", "flatcats", "flatmurray", "flattypewriter", "flatvan", "flatrum"]], "mapPin185673413": ["flatdiscgolfbasket", ["flatlou", "flatmatt", "flatrob", "flathammock", "flatdhs", "flatdiscgolfbasket", "flatflashlight", "flatcats", "flatmurray", "flattypewriter", "flatvan", "flatrum"]], "mapPin194464577": ["flatdhs", ["flatlou", "flatmatt", "flatrob", "flathammock", "flatdhs", "flatdiscgolfbasket", "flatflashlight", "flatcats", "flatmurray", "flattypewriter", "flatvan", "flatrum"]], "mapPin185671392": ["flatdiscgolfbasket", ["flatlou", "flatmatt", "flatrob", "flathammock", "flatdhs", "flatdiscgolfbasket", "flatflashlight", "flatcats", "flatmurray", "flattypewriter", "flatvan", "flatrum"]], "mapPin194503986": ["flatdhs", ["flatlou", "flatmatt", "flatrob", "flathammock", "flatdhs", "flatdiscgolfbasket", "flatflashlight", "flatcats", "flatmurray", "flattypewriter", "flatvan", "flatrum"]], "mapPin73459112": ["flathammock", ["flatlou", "flatmatt", "flatrob", "flathammock", "flatdhs", "flatdiscgolfbasket", "flatflashlight", "flatcats", "flatmurray", "flattypewriter", "flatvan", "flatrum"]], "mapPin193854289": ["flatdhs", ["flatlou", "flatmatt", "flatrob", "flathammock", "flatdhs", "flatdiscgolfbasket", "flatflashlight", "flatcats", "flatmurray", "flattypewriter", "flatvan", "flatrum"]], "mapPin73459119": ["flathammock", ["flatlou", "flatmatt", "flatrob", "flathammock", "flatdhs", "flatdiscgolfbasket", "flatflashlight", "flatcats", "flatmurray", "flattypewriter", "flatvan", "flatrum"]], "mapPin192936622": ["flatdhs", ["flatlou", "flatmatt", "flatrob", "flathammock", "flatdhs", "flatdiscgolfbasket", "flatflashlight", "flatcats", "flatmurray", "flattypewriter", "flatvan", "flatrum"]], "mapPin73459120": ["flathammock", ["flatlou", "flatmatt", "flatrob", "flathammock", "flatdhs", "flatdiscgolfbasket", "flatflashlight", "flatcats", "flatmurray", "flattypewriter", "flatvan", "flatrum"]], "mapPin181916735": ["flatdhs", ["flatlou", "flatmatt", "flatrob", "flathammock", "flatdhs", "flatdiscgolfbasket", "flatflashlight", "flatcats", "flatmurray", "flattypewriter", "flatvan", "flatrum"]], "mapPin194503980": ["flatdhs", ["flatlou", "flatmatt", "flatrob", "flathammock", "flatdhs", "flatdiscgolfbasket", "flatflashlight", "flatcats", "flatmurray", "flattypewriter", "flatvan", "flatrum"]], "mapPin194503979": ["flatdhs", ["flatlou", "flatmatt", "flatrob", "flathammock", "flatdhs", "flatdiscgolfbasket", "flatflashlight", "flatcats", "flatmurray", "flattypewriter", "flatvan", "flatrum"]], "mapPin185746366": ["flatdhs", ["flatlou", "flatmatt", "flatrob", "flathammock", "flatdhs", "flatdiscgolfbasket", "flatflashlight", "flatcats", "flatmurray", "flattypewriter", "flatvan", "flatrum"]], "mapPin187696276": ["flatdhs", ["flatlou", "flatmatt", "flatrob", "flathammock", "flatdhs", "flatdiscgolfbasket", "flatflashlight", "flatcats", "flatmurray", "flattypewriter", "flatvan", "flatrum"]], "mapPin185662405": ["flatdiscgolfbasket", ["flatlou", "flatmatt", "flatrob", "flathammock", "flatdhs", "flatdiscgolfbasket", "flatflashlight", "flatcats", "flatmurray", "flattypewriter", "flatvan", "flatrum"]], "mapPin185436882": ["flatdiscgolfbasket", ["flatlou", "flatmatt", "flatrob", "flathammock", "flatdhs", "flatdiscgolfbasket", "flatflashlight", "flatcats", "flatmurray", "flattypewriter", "flatvan", "flatrum"]], "mapPin185399812": ["flatdiscgolfbasket", ["flatlou", "flatmatt", "flatrob", "flathammock", "flatdhs", "flatdiscgolfbasket", "flatflashlight", "flatcats", "flatmurray", "flattypewriter", "flatvan", "flatrum"]], "mapPin194565542": ["flatdhs", ["flatlou", "flatmatt", "flatrob", "flathammock", "flatdhs", "flatdiscgolfbasket", "flatflashlight", "flatcats", "flatmurray", "flattypewriter", "flatvan", "flatrum"]], "mapPin73459121": ["flathammock", ["flatlou", "flatmatt", "flatrob", "flathammock", "flatdhs", "flatdiscgolfbasket", "flatflashlight", "flatcats", "flatmurray", "flattypewriter", "flatvan", "flatrum"]], "mapPin194523220": ["flatdhs", ["flatlou", "flatmatt", "flatrob", "flathammock", "flatdhs", "flatdiscgolfbasket", "flatflashlight", "flatcats", "flatmurray", "flattypewriter", "flatvan", "flatrum"]], "mapPin73459122": ["flathammock", ["flatlou", "flatmatt", "flatrob", "flathammock", "flatdhs", "flatdiscgolfbasket", "flatflashlight", "flatcats", "flatmurray", "flattypewriter", "flatvan", "flatrum"]], "mapPin194523219": ["flatdhs", ["flatlou", "flatmatt", "flatrob", "flathammock", "flatdhs", "flatdiscgolfbasket", "flatflashlight", "flatcats", "flatmurray", "flattypewriter", "flatvan", "flatrum"]], "mapPin194427695": ["flatrob", ["flatlou", "flatmatt", "flatrob", "flathammock", "flatdhs", "flatdiscgolfbasket", "flatflashlight", "flatcats", "flatmurray", "flattypewriter", "flatvan", "flatrum"]], "mapPin73459124": ["flathammock", ["flatlou", "flatmatt", "flatrob", "flathammock", "flatdhs", "flatdiscgolfbasket", "flatflashlight", "flatcats", "flatmurray", "flattypewriter", "flatvan", "flatrum"]], "mapPin73145675": ["flatrob", ["flatlou", "flatmatt", "flatrob", "flathammock", "flatdhs", "flatdiscgolfbasket", "flatflashlight", "flatcats", "flatmurray", "flattypewriter", "flatvan", "flatrum"]], "mapPin73546429": ["flatlou", ["flatlou", "flatmatt", "flatrob", "flathammock", "flatdhs", "flatdiscgolfbasket", "flatflashlight", "flatcats", "flatmurray", "flattypewriter", "flatvan", "flatrum"]], "mapPin194609772": ["flatdhs", ["flatlou", "flatmatt", "flatrob", "flathammock", "flatdhs", "flatdiscgolfbasket", "flatflashlight", "flatcats", "flatmurray", "flattypewriter", "flatvan", "flatrum"]], "mapPin191049554": ["flatdhs", ["flatlou", "flatmatt", "flatrob", "flathammock", "flatdhs", "flatdiscgolfbasket", "flatflashlight", "flatcats", "flatmurray", "flattypewriter", "flatvan", "flatrum"]], "mapPin189264342": ["flatdhs", ["flatlou", "flatmatt", "flatrob", "flathammock", "flatdhs", "flatdiscgolfbasket", "flatflashlight", "flatcats", "flatmurray", "flattypewriter", "flatvan", "flatrum"]], "mapPin183269336": ["flatdhs", ["flatlou", "flatmatt", "flatrob", "flathammock", "flatdhs", "flatdiscgolfbasket", "flatflashlight", "flatcats", "flatmurray", "flattypewriter", "flatvan", "flatrum"]], "mapPin73459125": ["flathammock", ["flatlou", "flatmatt", "flatrob", "flathammock", "flatdhs", "flatdiscgolfbasket", "flatflashlight", "flatcats", "flatmurray", "flattypewriter", "flatvan", "flatrum"]], "mapPin77728375": ["flatlou", ["flatlou", "flatmatt", "flatrob", "flathammock", "flatdhs", "flatdiscgolfbasket", "flatflashlight", "flatcats", "flatmurray", "flattypewriter", "flatvan", "flatrum"]], "mapPin73459126": ["flathammock", ["flatlou", "flatmatt", "flatrob", "flathammock", "flatdhs", "flatdiscgolfbasket", "flatflashlight", "flatcats", "flatmurray", "flattypewriter", "flatvan", "flatrum"]], "mapPin79086200": ["flatlou", ["flatlou", "flatmatt", "flatrob", "flathammock", "flatdhs", "flatdiscgolfbasket", "flatflashlight", "flatcats", "flatmurray", "flattypewriter", "flatvan", "flatrum"]], "mapPin65493492": ["flathammock", ["flatlou", "flatmatt", "flatrob", "flathammock", "flatdhs", "flatdiscgolfbasket", "flatflashlight", "flatcats", "flatmurray", "flattypewriter", "flatvan", "flatrum"]], "mapPin50119027": ["poivirtualgarden", "poivirtualgarden"]}, "undeployed": {"1694149881.9218683": ["agenthop/5360/", "38.2383759686549", "-84.5470702268472", ["flatlou", "flatmatt", "flatrob", "flathammock", "flatdhs", "flatdiscgolfbasket", "flatflashlight", "flatcats", "flatmurray", "flattypewriter", "flatvan", "flatrum"]], "1694149881.9261508": ["cadonkey/1175/", "38.2380770748446", "-84.5472206438699", ["flatlou", "flatmatt", "flatrob", "flathammock", "flatdhs", "flatdiscgolfbasket", "flatflashlight", "flatcats", "flatmurray", "flattypewriter", "flatvan", "flatrum"]], "1694149881.9263597": ["derlame/12088/", "38.2380896016373", "-84.5470383479781", ["flatlou", "flatmatt", "flatrob", "flathammock", "flatdhs", "flatdiscgolfbasket", "flatflashlight", "flatcats", "flatmurray", "flattypewriter", "flatvan", "flatrum"]], "1694149881.9268053": ["nexus69/2206/", "38.2381146552228", "-84.5466737561001", ["flatlou", "flatmatt", "flatrob", "flathammock", "flatdhs", "flatdiscgolfbasket", "flatflashlight", "flatcats", "flatmurray", "flattypewriter", "flatvan", "flatrum"]], "1694149881.927008": ["agenthop/5368/", "38.2378963109576", "-84.5477515905335", ["flatlou", "flatmatt", "flatrob", "flathammock", "flatdhs", "flatdiscgolfbasket", "flatflashlight", "flatcats", "flatmurray", "flattypewriter", "flatvan", "flatrum"]], "1694149881.9274707": ["cidinho/1820/", "38.2379213645431", "-84.5473869996247", ["flatlou", "flatmatt", "flatrob", "flathammock", "flatdhs", "flatdiscgolfbasket", "flatflashlight", "flatcats", "flatmurray", "flattypewriter", "flatvan", "flatrum"]], "1694149881.9277058": ["ltrangerbob/2325/", "38.2379338913358", "-84.5472047041232", ["flatlou", "flatmatt", "flatrob", "flathammock", "flatdhs", "flatdiscgolfbasket", "flatflashlight", "flatcats", "flatmurray", "flattypewriter", "flatvan", "flatrum"]], "1694149881.9279063": ["spacecoastgeostore/7322/", "38.2379464181286", "-84.5470224085903", ["flatlou", "flatmatt", "flatrob", "flathammock", "flatdhs", "flatdiscgolfbasket", "flatflashlight", "flatcats", "flatmurray", "flattypewriter", "flatvan", "flatrum"]], "1694149881.9281068": ["cidinho/1860/", "38.2379589449213", "-84.546840113026", ["flatlou", "flatmatt", "flatrob", "flathammock", "flatdhs", "flatdiscgolfbasket", "flatflashlight", "flatcats", "flatmurray", "flattypewriter", "flatvan", "flatrum"]], "1694149881.9290764": ["spacecoastgeostore/7330/", "38.2377656542415", "-84.5475533546616", ["flatlou", "flatmatt", "flatrob", "flathammock", "flatdhs", "flatdiscgolfbasket", "flatflashlight", "flatcats", "flatmurray", "flattypewriter", "flatvan", "flatrum"]], "1694149881.9307163": ["ltrangerbob/2335/", "38.237840814998", "-84.5464595835239", ["flatlou", "flatmatt", "flatrob", "flathammock", "flatdhs", "flatdiscgolfbasket", "flatflashlight", "flatcats", "flatmurray", "flattypewriter", "flatvan", "flatrum"]], "1694149881.93173": ["cidinho/1901/", "38.2378658685835", "-84.5460949928934", ["flatlou", "flatmatt", "flatrob", "flathammock", "flatdhs", "flatdiscgolfbasket", "flatflashlight", "flatcats", "flatmurray", "flattypewriter", "flatvan", "flatrum"]], "1694149881.931988": ["ltrangerbob/2356/", "38.2378783953762", "-84.545912697531", ["flatlou", "flatmatt", "flatrob", "flathammock", "flatdhs", "flatdiscgolfbasket", "flatflashlight", "flatcats", "flatmurray", "flattypewriter", "flatvan", "flatrum"]], "1694149881.934129": ["debolicious/8331/", "38.2376725779037", "-84.5468082350629", ["flatlou", "flatmatt", "flatrob", "flathammock", "flatdhs", "flatdiscgolfbasket", "flatflashlight", "flatcats", "flatmurray", "flattypewriter", "flatvan", "flatrum"]], "1694149881.934611": ["spacecoastgeostore/7417/", "38.2376976314892", "-84.546443645276", ["flatlou", "flatmatt", "flatrob", "flathammock", "flatdhs", "flatdiscgolfbasket", "flatflashlight", "flatcats", "flatmurray", "flattypewriter", "flatvan", "flatrum"]], "1694149881.9353213": ["spacecoastgeostore/7586/", "38.2377352118674", "-84.5458967603601", ["flatlou", "flatmatt", "flatrob", "flathammock", "flatdhs", "flatdiscgolfbasket", "flatflashlight", "flatcats", "flatmurray", "flattypewriter", "flatvan", "flatrum"]], "1694149881.9355152": ["agenthop/5993/", "38.2374667604312", "-84.5477037682508", ["flatlou", "flatmatt", "flatrob", "flathammock", "flatdhs", "flatdiscgolfbasket", "flatflashlight", "flatcats", "flatmurray", "flattypewriter", "flatvan", "flatrum"]], "1694149881.935967": ["ltrangerbob/2368/", "38.2374918140167", "-84.5473391794959", ["flatlou", "flatmatt", "flatrob", "flathammock", "flatdhs", "flatdiscgolfbasket", "flatflashlight", "flatcats", "flatmurray", "flattypewriter", "flatvan", "flatrum"]], "1694149881.9364166": ["spacecoastgeostore/7612/", "38.2375168676022", "-84.5469745906153", ["flatlou", "flatmatt", "flatrob", "flathammock", "flatdhs", "flatdiscgolfbasket", "flatflashlight", "flatcats", "flatmurray", "flattypewriter", "flatvan", "flatrum"]], "1694149881.936608": ["thistlemama/919/", "38.2375293943949", "-84.5467922961279", ["flatlou", "flatmatt", "flatrob", "flathammock", "flatdhs", "flatdiscgolfbasket", "flatflashlight", "flatcats", "flatmurray", "flattypewriter", "flatvan", "flatrum"]], "1694149881.9370546": ["emeraldangel/2534/", "38.2375544479804", "-84.546427707059", ["flatlou", "flatmatt", "flatrob", "flathammock", "flatdhs", "flatdiscgolfbasket", "flatflashlight", "flatcats", "flatmurray", "flattypewriter", "flatvan", "flatrum"]], "1694149881.9372473": ["debolicious/8265/", "38.2375669747731", "-84.5462454124774", ["flatlou", "flatmatt", "flatrob", "flathammock", "flatdhs", "flatdiscgolfbasket", "flatflashlight", "flatcats", "flatmurray", "flattypewriter", "flatvan", "flatrum"]], "1694149881.937716": ["emeraldangel/2515/", "38.2375920283586", "-84.54588082322", ["flatlou", "flatmatt", "flatrob", "flathammock", "flatdhs", "flatdiscgolfbasket", "flatflashlight", "flatcats", "flatmurray", "flattypewriter", "flatvan", "flatrum"]], "1694149881.9379272": ["debolicious/8195/", "38.2376045551514", "-84.5456985285442", ["flatlou", "flatmatt", "flatrob", "flathammock", "flatdhs", "flatdiscgolfbasket", "flatflashlight", "flatcats", "flatmurray", "flattypewriter", "flatvan", "flatrum"]], "1694149881.9383845": ["david/4791/", "38.2373361037151", "-84.5475055335499", ["flatlou", "flatmatt", "flatrob", "flathammock", "flatdhs", "flatdiscgolfbasket", "flatflashlight", "flatcats", "flatmurray", "flattypewriter", "flatvan", "flatrum"]], "1694149881.9388404": ["rgk76/1041/", "38.2373611573006", "-84.5471409454501", ["flatlou", "flatmatt", "flatrob", "flathammock", "flatdhs", "flatdiscgolfbasket", "flatflashlight", "flatcats", "flatmurray", "flattypewriter", "flatvan", "flatrum"]], "1694149881.939046": ["david/4843/", "38.2373736840934", "-84.5469586513531", ["flatlou", "flatmatt", "flatrob", "flathammock", "flatdhs", "flatdiscgolfbasket", "flatflashlight", "flatcats", "flatmurray", "flattypewriter", "flatvan", "flatrum"]], "1694149881.9392514": ["iscreambiue/1133/", "38.2373862108861", "-84.5467763572247", ["flatlou", "flatmatt", "flatrob", "flathammock", "flatdhs", "flatdiscgolfbasket", "flatflashlight", "flatcats", "flatmurray", "flattypewriter", "flatvan", "flatrum"]], "1694149881.9397047": ["mpeters82/2131/", "38.2374112644716", "-84.5464117688737", ["flatlou", "flatmatt", "flatrob", "flathammock", "flatdhs", "flatdiscgolfbasket", "flatflashlight", "flatcats", "flatmurray", "flattypewriter", "flatvan", "flatrum"]], "1694149881.9401643": ["zappa/548/", "38.2374363180571", "-84.5460471803971", ["flatlou", "flatmatt", "flatrob", "flathammock", "flatdhs", "flatdiscgolfbasket", "flatflashlight", "flatcats", "flatmurray", "flattypewriter", "flatvan", "flatrum"]], "1694149881.9406176": ["squirrelwithsombrero/573/", "38.2374613716426", "-84.5456825917949", ["flatlou", "flatmatt", "flatrob", "flathammock", "flatdhs", "flatdiscgolfbasket", "flatflashlight", "flatcats", "flatmurray", "flattypewriter", "flatvan", "flatrum"]], "1694149881.9411077": ["eagledadandxenia/19035/", "38.2371803934136", "-84.547671886886", ["flatlou", "flatmatt", "flatrob", "flathammock", "flatdhs", "flatdiscgolfbasket", "flatflashlight", "flatcats", "flatmurray", "flattypewriter", "flatvan", "flatrum"]], "1694149881.9415715": ["debolicious/8184/", "38.2372054469991", "-84.547307299567", ["flatlou", "flatmatt", "flatrob", "flathammock", "flatdhs", "flatdiscgolfbasket", "flatflashlight", "flatcats", "flatmurray", "flattypewriter", "flatvan", "flatrum"]], "1694149881.9417722": ["eagledadandxenia/18963/", "38.2372179737918", "-84.5471250058603", ["flatlou", "flatmatt", "flatrob", "flathammock", "flatdhs", "flatdiscgolfbasket", "flatflashlight", "flatcats", "flatmurray", "flattypewriter", "flatvan", "flatrum"]], "1694149881.9422157": ["debolicious/8132/", "38.2372430273773", "-84.5467604183529", ["flatlou", "flatmatt", "flatrob", "flathammock", "flatdhs", "flatdiscgolfbasket", "flatflashlight", "flatcats", "flatmurray", "flattypewriter", "flatvan", "flatrum"]], "1694149881.9424756": ["eagledadandxenia/18598/", "38.2372555541701", "-84.546578124552", ["flatlou", "flatmatt", "flatrob", "flathammock", "flatdhs", "flatdiscgolfbasket", "flatflashlight", "flatcats", "flatmurray", "flattypewriter", "flatvan", "flatrum"]], "1694149881.943187": ["eagledadandxenia/18243/", "38.2372931345483", "-84.5460312429611", ["flatlou", "flatmatt", "flatrob", "flathammock", "flatdhs", "flatdiscgolfbasket", "flatflashlight", "flatcats", "flatmurray", "flattypewriter", "flatvan", "flatrum"]], "1694149881.9438784": ["eagledadandxenia/18193/", "38.2373307149265", "-84.5454843610875", ["flatlou", "flatmatt", "flatrob", "flathammock", "flatdhs", "flatdiscgolfbasket", "flatflashlight", "flatcats", "flatmurray", "flattypewriter", "flatvan", "flatrum"]], "1694149881.944379": ["cidinho/1915/", "38.2370497366975", "-84.5474736529654", ["flatlou", "flatmatt", "flatrob", "flathammock", "flatdhs", "flatdiscgolfbasket", "flatflashlight", "flatcats", "flatmurray", "flattypewriter", "flatvan", "flatrum"]], "1694149881.94507": ["newfruit/6300/", "38.2370873170758", "-84.5469267729225", ["flatlou", "flatmatt", "flatrob", "flathammock", "flatdhs", "flatdiscgolfbasket", "flatflashlight", "flatcats", "flatmurray", "flattypewriter", "flatvan", "flatrum"]], "1694149881.9455323": ["archieruby/606/", "38.2371123706613", "-84.5465621860701", ["flatlou", "flatmatt", "flatrob", "flathammock", "flatdhs", "flatdiscgolfbasket", "flatflashlight", "flatcats", "flatmurray", "flattypewriter", "flatvan", "flatrum"]], "1694149881.9459832": ["debolicious/7987/", "38.2371374242468", "-84.5461975990921", ["flatlou", "flatmatt", "flatrob", "flathammock", "flatdhs", "flatdiscgolfbasket", "flatflashlight", "flatcats", "flatmurray", "flattypewriter", "flatvan", "flatrum"]], "1694149881.9464197": ["squonk/2556/", "38.2371624778323", "-84.5458330119886", ["flatlou", "flatmatt", "flatrob", "flathammock", "flatdhs", "flatdiscgolfbasket", "flatflashlight", "flatcats", "flatmurray", "flattypewriter", "flatvan", "flatrum"]], "1694149881.9466276": ["debolicious/7981/", "38.237175004625", "-84.5456507183897", ["flatlou", "flatmatt", "flatrob", "flathammock", "flatdhs", "flatdiscgolfbasket", "flatflashlight", "flatcats", "flatmurray", "flattypewriter", "flatvan", "flatrum"]], "1694149881.9470596": ["vamtrix/2130/", "38.2372000582105", "-84.5452861310977", ["flatlou", "flatmatt", "flatrob", "flathammock", "flatdhs", "flatdiscgolfbasket", "flatflashlight", "flatcats", "flatmurray", "flattypewriter", "flatvan", "flatrum"]], "1694149881.9472458": ["debolicious/7926/", "38.2372125850033", "-84.5451038374046", ["flatlou", "flatmatt", "flatrob", "flathammock", "flatdhs", "flatdiscgolfbasket", "flatflashlight", "flatcats", "flatmurray", "flattypewriter", "flatvan", "flatrum"]], "1694149881.9484744": ["meanderingmonkeys/15908/", "38.2369566603597", "-84.5467285407025", ["flatlou", "flatmatt", "flatrob", "flathammock", "flatdhs", "flatdiscgolfbasket", "flatflashlight", "flatcats", "flatmurray", "flattypewriter", "flatvan", "flatrum"]], "1694149881.9486623": ["maxi72/1742/", "38.2369691871525", "-84.5465462476196", ["flatlou", "flatmatt", "flatrob", "flathammock", "flatdhs", "flatdiscgolfbasket", "flatflashlight", "flatcats", "flatmurray", "flattypewriter", "flatvan", "flatrum"]], "1694149881.9493432": ["thistlemama/925/", "38.2370067675307", "-84.5459993681824", ["flatlou", "flatmatt", "flatrob", "flathammock", "flatdhs", "flatdiscgolfbasket", "flatflashlight", "flatcats", "flatmurray", "flattypewriter", "flatvan", "flatrum"]], "1694149881.949781": ["coffeeeater/3564/", "38.2370318211163", "-84.5456347817339", ["flatlou", "flatmatt", "flatrob", "flathammock", "flatdhs", "flatdiscgolfbasket", "flatflashlight", "flatcats", "flatmurray", "flattypewriter", "flatvan", "flatrum"]], "1694149881.9499698": ["mattie/10318/", "38.237044347909", "-84.5454524884626", ["flatlou", "flatmatt", "flatrob", "flathammock", "flatdhs", "flatdiscgolfbasket", "flatflashlight", "flatcats", "flatmurray", "flattypewriter", "flatvan", "flatrum"]], "1694149881.9509106": ["eagledadandxenia/18080/", "38.2367884232654", "-84.5470771872783", ["flatlou", "flatmatt", "flatrob", "flathammock", "flatdhs", "flatdiscgolfbasket", "flatflashlight", "flatcats", "flatmurray", "flattypewriter", "flatvan", "flatrum"]], "1694149881.951099": ["curt360/5448/", "38.2368009500582", "-84.5468948946172", ["flatlou", "flatmatt", "flatrob", "flathammock", "flatdhs", "flatdiscgolfbasket", "flatflashlight", "flatcats", "flatmurray", "flattypewriter", "flatvan", "flatrum"]], "1694149881.951537": ["eagledadandxenia/18038/", "38.2368260036437", "-84.5465303092007", ["flatlou", "flatmatt", "flatrob", "flathammock", "flatdhs", "flatdiscgolfbasket", "flatflashlight", "flatcats", "flatmurray", "flattypewriter", "flatvan", "flatrum"]], "1694149881.9524887": ["flatblack/542/", "38.2368761108147", "-84.5458011379909", ["flatlou", "flatmatt", "flatrob", "flathammock", "flatdhs", "flatdiscgolfbasket", "flatflashlight", "flatcats", "flatmurray", "flattypewriter", "flatvan", "flatrum"]], "1694149881.952923": ["arendt/2716/", "38.2369011644002", "-84.5454365521975", ["flatlou", "flatmatt", "flatrob", "flathammock", "flatdhs", "flatdiscgolfbasket", "flatflashlight", "flatcats", "flatmurray", "flattypewriter", "flatvan", "flatrum"]], "1694149881.953609": ["squonk/2537/", "38.236582605793", "-84.5479727088537", ["flatlou", "flatmatt", "flatrob", "flathammock", "flatdhs", "flatdiscgolfbasket", "flatflashlight", "flatcats", "flatmurray", "flattypewriter", "flatvan", "flatrum"]], "1694149881.9543204": ["squonk/2533/", "38.2366201861713", "-84.547425832324", ["flatlou", "flatmatt", "flatrob", "flathammock", "flatdhs", "flatdiscgolfbasket", "flatflashlight", "flatcats", "flatmurray", "flattypewriter", "flatvan", "flatrum"]], "1694149881.9547575": ["jeffeth/1365/", "38.2366452397568", "-84.5470612478138", ["flatlou", "flatmatt", "flatrob", "flathammock", "flatdhs", "flatdiscgolfbasket", "flatflashlight", "flatcats", "flatmurray", "flattypewriter", "flatvan", "flatrum"]], "1694149881.9549434": ["squonk/2513/", "38.2366577665495", "-84.5468789555116", ["flatlou", "flatmatt", "flatrob", "flathammock", "flatdhs", "flatdiscgolfbasket", "flatflashlight", "flatcats", "flatmurray", "flattypewriter", "flatvan", "flatrum"]], "1694149881.9556274": ["squonk/2486/", "38.2366953469278", "-84.5463320784166", ["flatlou", "flatmatt", "flatrob", "flathammock", "flatdhs", "flatdiscgolfbasket", "flatflashlight", "flatcats", "flatmurray", "flattypewriter", "flatvan", "flatrum"]], "1694149881.9563484": ["squonk/2474/", "38.236732927306", "-84.545785201039", ["flatlou", "flatmatt", "flatrob", "flathammock", "flatdhs", "flatdiscgolfbasket", "flatflashlight", "flatcats", "flatmurray", "flattypewriter", "flatvan", "flatrum"]], "1694149881.9568183": ["searays2/776/", "38.2367579808915", "-84.5454206159636", ["flatlou", "flatmatt", "flatrob", "flathammock", "flatdhs", "flatdiscgolfbasket", "flatflashlight", "flatcats", "flatmurray", "flattypewriter", "flatvan", "flatrum"]], "1694149881.9570224": ["squonk/2465/", "38.2367705076843", "-84.5452383233788", ["flatlou", "flatmatt", "flatrob", "flathammock", "flatdhs", "flatdiscgolfbasket", "flatflashlight", "flatcats", "flatmurray", "flattypewriter", "flatvan", "flatrum"]], "1694149881.9574654": ["bonnieb1/4053/", "38.2364394222843", "-84.5479567676258", ["flatlou", "flatmatt", "flatrob", "flathammock", "flatdhs", "flatdiscgolfbasket", "flatflashlight", "flatcats", "flatmurray", "flattypewriter", "flatvan", "flatrum"]], "1694149881.957942": ["hansyd22/314/", "38.2364644758698", "-84.547592184022", ["flatlou", "flatmatt", "flatrob", "flathammock", "flatdhs", "flatdiscgolfbasket", "flatflashlight", "flatcats", "flatmurray", "flattypewriter", "flatvan", "flatrum"]], "1694149881.958165": ["cidinho/2017/", "38.2364770026625", "-84.547409892173", ["flatlou", "flatmatt", "flatrob", "flathammock", "flatdhs", "flatdiscgolfbasket", "flatflashlight", "flatcats", "flatmurray", "flattypewriter", "flatvan", "flatrum"]], "1694149881.9583678": ["maattmoo/1414/", "38.2364895294553", "-84.5472276002926", ["flatlou", "flatmatt", "flatrob", "flathammock", "flatdhs", "flatdiscgolfbasket", "flatflashlight", "flatcats", "flatmurray", "flattypewriter", "flatvan", "flatrum"]], "1694149881.958566": ["noisette/2027/", "38.2365020562481", "-84.5470453083808", ["flatlou", "flatmatt", "flatrob", "flathammock", "flatdhs", "flatdiscgolfbasket", "flatflashlight", "flatcats", "flatmurray", "flattypewriter", "flatvan", "flatrum"]], "1694149881.9587653": ["citygalbex/875/", "38.2365145830408", "-84.5468630164376", ["flatlou", "flatmatt", "flatrob", "flathammock", "flatdhs", "flatdiscgolfbasket", "flatflashlight", "flatcats", "flatmurray", "flattypewriter", "flatvan", "flatrum"]], "1694149881.9594705": ["flatblack/556/", "38.2365521634191", "-84.5463161404195", ["flatlou", "flatmatt", "flatrob", "flathammock", "flatdhs", "flatdiscgolfbasket", "flatflashlight", "flatcats", "flatmurray", "flattypewriter", "flatvan", "flatrum"]], "1694149881.9596715": ["dev63/630/", "38.2365646902118", "-84.5461338483506", ["flatlou", "flatmatt", "flatrob", "flathammock", "flatdhs", "flatdiscgolfbasket", "flatflashlight", "flatcats", "flatmurray", "flattypewriter", "flatvan", "flatrum"]], "1694149881.960113": ["jeffeth/2559/", "38.2365897437973", "-84.5457692641187", ["flatlou", "flatmatt", "flatrob", "flathammock", "flatdhs", "flatdiscgolfbasket", "flatflashlight", "flatcats", "flatmurray", "flattypewriter", "flatvan", "flatrum"]], "1694149881.960857": ["v1ncenzo/4319/", "38.2366273241756", "-84.5452223875353", ["flatlou", "flatmatt", "flatrob", "flathammock", "flatdhs", "flatdiscgolfbasket", "flatflashlight", "flatcats", "flatmurray", "flattypewriter", "flatvan", "flatrum"]], "1694149881.9610713": ["dev63/602/", "38.2363588727393", "-84.5470293689787", ["flatlou", "flatmatt", "flatrob", "flathammock", "flatdhs", "flatdiscgolfbasket", "flatflashlight", "flatcats", "flatmurray", "flattypewriter", "flatvan", "flatrum"]], "1694149881.9615207": ["ohail/15523/", "38.2363839263248", "-84.5466647857788", ["flatlou", "flatmatt", "flatrob", "flathammock", "flatdhs", "flatdiscgolfbasket", "flatflashlight", "flatcats", "flatmurray", "flattypewriter", "flatvan", "flatrum"]], "1694149881.9617333": ["jeffeth/2563/", "38.2363964531176", "-84.5464824941317", ["flatlou", "flatmatt", "flatrob", "flathammock", "flatdhs", "flatdiscgolfbasket", "flatflashlight", "flatcats", "flatmurray", "flattypewriter", "flatvan", "flatrum"]], "1694149881.9619453": ["arendt/3214/", "38.2364089799103", "-84.5463002024532", ["flatlou", "flatmatt", "flatrob", "flathammock", "flatdhs", "flatdiscgolfbasket", "flatflashlight", "flatcats", "flatmurray", "flattypewriter", "flatvan", "flatrum"]], "1694149881.962147": ["mrshb31/5714/", "38.2364215067031", "-84.5461179107433", ["flatlou", "flatmatt", "flatrob", "flathammock", "flatdhs", "flatdiscgolfbasket", "flatflashlight", "flatcats", "flatmurray", "flattypewriter", "flatvan", "flatrum"]], "1694149881.962345": ["hb31/5599/", "38.2364340334959", "-84.545935619002", ["flatlou", "flatmatt", "flatrob", "flathammock", "flatdhs", "flatdiscgolfbasket", "flatflashlight", "flatcats", "flatmurray", "flattypewriter", "flatvan", "flatrum"]], "1694149881.9625423": ["coffeeeater/5367/", "38.2364465602886", "-84.5457533272293", ["flatlou", "flatmatt", "flatrob", "flathammock", "flatdhs", "flatdiscgolfbasket", "flatflashlight", "flatcats", "flatmurray", "flattypewriter", "flatvan", "flatrum"]], "1694149881.9627342": ["quietriots/521/", "38.2364590870814", "-84.5455710354252", ["flatlou", "flatmatt", "flatrob", "flathammock", "flatdhs", "flatdiscgolfbasket", "flatflashlight", "flatcats", "flatmurray", "flattypewriter", "flatvan", "flatrum"]], "1694149881.9629164": ["hb31/5657/", "38.2364716138741", "-84.5453887435898", ["flatlou", "flatmatt", "flatrob", "flathammock", "flatdhs", "flatdiscgolfbasket", "flatflashlight", "flatcats", "flatmurray", "flattypewriter", "flatvan", "flatrum"]], "1694149881.96412": ["coffeeeater/3138/", "38.2362532696088", "-84.5464665558382", ["flatlou", "flatmatt", "flatrob", "flathammock", "flatdhs", "flatdiscgolfbasket", "flatflashlight", "flatcats", "flatmurray", "flattypewriter", "flatvan", "flatrum"]], "1694149881.9643462": ["squonk/2449/", "38.2362657964016", "-84.5462842645187", ["flatlou", "flatmatt", "flatrob", "flathammock", "flatdhs", "flatdiscgolfbasket", "flatflashlight", "flatcats", "flatmurray", "flattypewriter", "flatvan", "flatrum"]], "1694149881.9648051": ["v1ncenzo/4311/", "38.2362908499871", "-84.5459196817854", ["flatlou", "flatmatt", "flatrob", "flathammock", "flatdhs", "flatdiscgolfbasket", "flatflashlight", "flatcats", "flatmurray", "flattypewriter", "flatvan", "flatrum"]], "1694149881.9650116": ["squonk/2434/", "38.2363033767799", "-84.5457373903717", ["flatlou", "flatmatt", "flatrob", "flathammock", "flatdhs", "flatdiscgolfbasket", "flatflashlight", "flatcats", "flatmurray", "flattypewriter", "flatvan", "flatrum"]], "1694149881.9657319": ["squonk/2406/", "38.2363409571581", "-84.545190515942", ["flatlou", "flatmatt", "flatrob", "flathammock", "flatdhs", "flatdiscgolfbasket", "flatflashlight", "flatcats", "flatmurray", "flattypewriter", "flatvan", "flatrum"]], "1694149881.966438": ["v1ncenzo/4288/", "38.2363785375364", "-84.5446436412298", ["flatlou", "flatmatt", "flatrob", "flathammock", "flatdhs", "flatdiscgolfbasket", "flatflashlight", "flatcats", "flatmurray", "flattypewriter", "flatvan", "flatrum"]], "1694149881.966664": ["rgk76/1032/", "38.2360850325145", "-84.5468151994025", ["flatlou", "flatmatt", "flatrob", "flathammock", "flatdhs", "flatdiscgolfbasket", "flatflashlight", "flatcats", "flatmurray", "flattypewriter", "flatvan", "flatrum"]], "1694149881.9680054": ["nbtzyy2/2066/", "38.2361476664783", "-84.5459037445996", ["flatlou", "flatmatt", "flatrob", "flathammock", "flatdhs", "flatdiscgolfbasket", "flatflashlight", "flatcats", "flatmurray", "flattypewriter", "flatvan", "flatrum"]], "1694149881.968253": ["dev63/690/", "38.236160193271", "-84.5457214535449", ["flatlou", "flatmatt", "flatrob", "flathammock", "flatdhs", "flatdiscgolfbasket", "flatflashlight", "flatcats", "flatmurray", "flattypewriter", "flatvan", "flatrum"]], "1694149881.9687238": ["v1ncenzo/4285/", "38.2361852468565", "-84.545356871341", ["flatlou", "flatmatt", "flatrob", "flathammock", "flatdhs", "flatdiscgolfbasket", "flatflashlight", "flatcats", "flatmurray", "flattypewriter", "flatvan", "flatrum"]], "1694149881.968948": ["1shemarine/8863/", "38.2361977736493", "-84.545174580192", ["flatlou", "flatmatt", "flatrob", "flathammock", "flatdhs", "flatdiscgolfbasket", "flatflashlight", "flatcats", "flatmurray", "flattypewriter", "flatvan", "flatrum"]], "1694149881.9694214": ["david/13298/", "38.2362228272348", "-84.5448099977998", ["flatlou", "flatmatt", "flatrob", "flathammock", "flatdhs", "flatdiscgolfbasket", "flatflashlight", "flatcats", "flatmurray", "flattypewriter", "flatvan", "flatrum"]], "1694149881.9698815": ["v1ncenzo/4258/", "38.2359293222129", "-84.5469815509612", ["flatlou", "flatmatt", "flatrob", "flathammock", "flatdhs", "flatdiscgolfbasket", "flatflashlight", "flatcats", "flatmurray", "flattypewriter", "flatvan", "flatrum"]], "1694149881.9701042": ["ohail/27894/", "38.2359418490057", "-84.5467992604537", ["flatlou", "flatmatt", "flatrob", "flathammock", "flatdhs", "flatdiscgolfbasket", "flatflashlight", "flatcats", "flatmurray", "flattypewriter", "flatvan", "flatrum"]], "1694149881.9703424": ["turtle/9665/", "38.2359543757984", "-84.5466169699149", ["flatlou", "flatmatt", "flatrob", "flathammock", "flatdhs", "flatdiscgolfbasket", "flatflashlight", "flatcats", "flatmurray", "flattypewriter", "flatvan", "flatrum"]], "1694149881.9705517": ["hawg/7237/", "38.236029536555", "-84.5455232260225", ["flatlou", "flatmatt", "flatrob", "flathammock", "flatdhs", "flatdiscgolfbasket", "flatflashlight", "flatcats", "flatmurray", "flattypewriter", "flatvan", "flatrum"]], "1694149881.9712982": ["ohail/27895/", "38.2360921705188", "-84.5446117719151", ["flatlou", "flatmatt", "flatrob", "flathammock", "flatdhs", "flatdiscgolfbasket", "flatflashlight", "flatcats", "flatmurray", "flattypewriter", "flatvan", "flatrum"]], "1694149881.9715087": ["rikitan/2202/", "38.2361046973116", "-84.5444294809995", ["flatlou", "flatmatt", "flatrob", "flathammock", "flatdhs", "flatdiscgolfbasket", "flatflashlight", "flatcats", "flatmurray", "flattypewriter", "flatvan", "flatrum"]], "1694149881.9724817": ["arendt/1986/", "38.235898879839", "-84.5453249992177", ["flatlou", "flatmatt", "flatrob", "flathammock", "flatdhs", "flatdiscgolfbasket", "flatflashlight", "flatcats", "flatmurray", "flattypewriter", "flatvan", "flatrum"]], "1694149881.9727037": ["squonk/2376/", "38.2359114066317", "-84.5451427087866", ["flatlou", "flatmatt", "flatrob", "flathammock", "flatdhs", "flatdiscgolfbasket", "flatflashlight", "flatcats", "flatmurray", "flattypewriter", "flatvan", "flatrum"]], "1694149881.9731767": ["bonnieb1/9925/", "38.2356304284026", "-84.5471319621978", ["flatlou", "flatmatt", "flatrob", "flathammock", "flatdhs", "flatdiscgolfbasket", "flatflashlight", "flatcats", "flatmurray", "flattypewriter", "flatvan", "flatrum"]], "1694149881.9739115": ["1shemarine/10189/", "38.2356680087809", "-84.5465850928292", ["flatlou", "flatmatt", "flatrob", "flathammock", "flatdhs", "flatdiscgolfbasket", "flatflashlight", "flatcats", "flatmurray", "flattypewriter", "flatvan", "flatrum"]], "1694149881.9741359": ["v1ncenzo/4256/", "38.2356805355736", "-84.5464028029769", ["flatlou", "flatmatt", "flatrob", "flathammock", "flatdhs", "flatdiscgolfbasket", "flatflashlight", "flatcats", "flatmurray", "flattypewriter", "flatvan", "flatrum"]], "1694149881.974867": ["v1ncenzo/4251/", "38.2357181159519", "-84.5458559332314", ["flatlou", "flatmatt", "flatrob", "flathammock", "flatdhs", "flatdiscgolfbasket", "flatflashlight", "flatcats", "flatmurray", "flattypewriter", "flatvan", "flatrum"]], "1694149881.975582": ["v1ncenzo/4243/", "38.2357556963302", "-84.5453090632033", ["flatlou", "flatmatt", "flatrob", "flathammock", "flatdhs", "flatdiscgolfbasket", "flatflashlight", "flatcats", "flatmurray", "flattypewriter", "flatvan", "flatrum"]], "1694149881.9760787": ["ohail/33283/", "38.2354872448937", "-84.5471160226248", ["flatlou", "flatmatt", "flatrob", "flathammock", "flatdhs", "flatdiscgolfbasket", "flatflashlight", "flatcats", "flatmurray", "flattypewriter", "flatvan", "flatrum"]], "1694149881.9762926": ["v1ncenzo/4240/", "38.2354997716865", "-84.5469337332256", ["flatlou", "flatmatt", "flatrob", "flathammock", "flatdhs", "flatdiscgolfbasket", "flatflashlight", "flatcats", "flatmurray", "flattypewriter", "flatvan", "flatrum"]], "1694149881.9767551": ["thebitbandit/5194/", "38.235524825272", "-84.546569154333", ["flatlou", "flatmatt", "flatrob", "flathammock", "flatdhs", "flatdiscgolfbasket", "flatflashlight", "flatcats", "flatmurray", "flattypewriter", "flatvan", "flatrum"]], "1694149881.9774706": ["1shemarine/10195/", "38.2355624056503", "-84.5460222857586", ["flatlou", "flatmatt", "flatrob", "flathammock", "flatdhs", "flatdiscgolfbasket", "flatflashlight", "flatcats", "flatmurray", "flattypewriter", "flatvan", "flatrum"]], "1694149881.977826": ["darthmaulmax/15514/", "38.2355749324431", "-84.545839996171", ["flatlou", "flatmatt", "flatrob", "flathammock", "flatdhs", "flatdiscgolfbasket", "flatflashlight", "flatcats", "flatmurray", "flattypewriter", "flatvan", "flatrum"]], "1694149881.9782922": ["vamtrix/3814/", "38.2355999860286", "-84.5454754169016", ["flatlou", "flatmatt", "flatrob", "flathammock", "flatdhs", "flatdiscgolfbasket", "flatflashlight", "flatcats", "flatmurray", "flattypewriter", "flatvan", "flatrum"]], "1694149881.9784806": ["buckeyecacher111/10859/", "38.2356125128214", "-84.5452931272198", ["flatlou", "flatmatt", "flatrob", "flathammock", "flatdhs", "flatdiscgolfbasket", "flatflashlight", "flatcats", "flatmurray", "flattypewriter", "flatvan", "flatrum"]], "1694149881.9794443": ["archieruby/766/", "38.2353816417633", "-84.5465532158683", ["flatlou", "flatmatt", "flatrob", "flathammock", "flatdhs", "flatdiscgolfbasket", "flatflashlight", "flatcats", "flatmurray", "flattypewriter", "flatvan", "flatrum"]], "1694149881.9796317": ["vaivag/436/", "38.235394168556", "-84.5463709267338", ["flatlou", "flatmatt", "flatrob", "flathammock", "flatdhs", "flatdiscgolfbasket", "flatflashlight", "flatcats", "flatmurray", "flattypewriter", "flatvan", "flatrum"]], "1694149881.9800708": ["spanol/3669/", "38.2354192221416", "-84.5460063483707", ["flatlou", "flatmatt", "flatrob", "flathammock", "flatdhs", "flatdiscgolfbasket", "flatflashlight", "flatcats", "flatmurray", "flattypewriter", "flatvan", "flatrum"]], "1694149881.9807596": ["1shemarine/10187/", "38.2354568025198", "-84.5454594805904", ["flatlou", "flatmatt", "flatrob", "flathammock", "flatdhs", "flatdiscgolfbasket", "flatflashlight", "flatcats", "flatmurray", "flattypewriter", "flatvan", "flatrum"]], "1694149881.9814847": ["flamingoflurrier/9565/", "38.2352384582545", "-84.5465372774348", ["flatlou", "flatmatt", "flatrob", "flathammock", "flatdhs", "flatdiscgolfbasket", "flatflashlight", "flatcats", "flatmurray", "flattypewriter", "flatvan", "flatrum"]], "1694149881.981673": ["mattie/10483/", "38.2352509850472", "-84.5463549886593", ["flatlou", "flatmatt", "flatrob", "flathammock", "flatdhs", "flatdiscgolfbasket", "flatflashlight", "flatcats", "flatmurray", "flattypewriter", "flatvan", "flatrum"]], "1694149881.981859": ["v1ncenzo/4235/", "38.23526351184", "-84.5461726998523", ["flatlou", "flatmatt", "flatrob", "flathammock", "flatdhs", "flatdiscgolfbasket", "flatflashlight", "flatcats", "flatmurray", "flattypewriter", "flatvan", "flatrum"]], "1694149881.9825525": ["v1ncenzo/4227/", "38.2353010922183", "-84.5456258332431", ["flatlou", "flatmatt", "flatrob", "flathammock", "flatdhs", "flatdiscgolfbasket", "flatflashlight", "flatcats", "flatmurray", "flattypewriter", "flatvan", "flatrum"]], "1694149881.983239": ["v1ncenzo/4225/", "38.2350827479529", "-84.5467036274183", ["flatlou", "flatmatt", "flatrob", "flathammock", "flatdhs", "flatdiscgolfbasket", "flatflashlight", "flatcats", "flatmurray", "flattypewriter", "flatvan", "flatrum"]], "1694149881.9839292": ["1shemarine/7239/", "38.2351203283312", "-84.5461567621684", ["flatlou", "flatmatt", "flatrob", "flathammock", "flatdhs", "flatdiscgolfbasket", "flatflashlight", "flatcats", "flatmurray", "flattypewriter", "flatvan", "flatrum"]], "1694149881.9846532": ["vamtrix/4923/", "38.2351579087095", "-84.545609896636", ["flatlou", "flatmatt", "flatrob", "flathammock", "flatdhs", "flatdiscgolfbasket", "flatflashlight", "flatcats", "flatmurray", "flattypewriter", "flatvan", "flatrum"]], "1694149881.9856184": ["vamtrix/4922/", "38.2349520912369", "-84.5465054006622", ["flatlou", "flatmatt", "flatrob", "flathammock", "flatdhs", "flatdiscgolfbasket", "flatflashlight", "flatcats", "flatmurray", "flattypewriter", "flatvan", "flatrum"]], "1694149881.9865742": ["wanderingaus/27184/", "38.2350021984079", "-84.5457762482431", ["flatlou", "flatmatt", "flatrob", "flathammock", "flatdhs", "flatdiscgolfbasket", "flatflashlight", "flatcats", "flatmurray", "flattypewriter", "flatvan", "flatrum"]], "1694149881.9872613": ["1shemarine/10193/", "38.2350397787862", "-84.545229383599", ["flatlou", "flatmatt", "flatrob", "flathammock", "flatdhs", "flatdiscgolfbasket", "flatflashlight", "flatcats", "flatmurray", "flattypewriter", "flatvan", "flatrum"]], "1694149881.987772": ["aufbau/15216/", "38.2348089077281", "-84.546489462323", ["flatlou", "flatmatt", "flatrob", "flathammock", "flatdhs", "flatdiscgolfbasket", "flatflashlight", "flatcats", "flatmurray", "flattypewriter", "flatvan", "flatrum"]], "1694149881.987979": ["wanderingaus/27383/", "38.2348214345209", "-84.5463071746243", ["flatlou", "flatmatt", "flatrob", "flathammock", "flatdhs", "flatdiscgolfbasket", "flatflashlight", "flatcats", "flatmurray", "flattypewriter", "flatvan", "flatrum"]], "1694149881.9886658": ["citygalbex/5364/", "38.2348590148991", "-84.5457603113396", ["flatlou", "flatmatt", "flatrob", "flathammock", "flatdhs", "flatdiscgolfbasket", "flatflashlight", "flatcats", "flatmurray", "flattypewriter", "flatvan", "flatrum"]], "1694149881.9888885": ["bojenris/195/", "38.2348715416919", "-84.5455780235153", ["flatlou", "flatmatt", "flatrob", "flathammock", "flatdhs", "flatdiscgolfbasket", "flatflashlight", "flatcats", "flatmurray", "flattypewriter", "flatvan", "flatrum"]], "1694149881.989332": ["wanderingaus/27428/", "38.2348965952774", "-84.5452134477723", ["flatlou", "flatmatt", "flatrob", "flathammock", "flatdhs", "flatdiscgolfbasket", "flatflashlight", "flatcats", "flatmurray", "flattypewriter", "flatvan", "flatrum"]], "1694149881.989534": ["v1ncenzo/4219/", "38.2346531974265", "-84.5466558113237", ["flatlou", "flatmatt", "flatrob", "flathammock", "flatdhs", "flatdiscgolfbasket", "flatflashlight", "flatcats", "flatmurray", "flattypewriter", "flatvan", "flatrum"]], "1694149881.989981": ["mattie/9956/", "38.2346782510121", "-84.5462912366754", ["flatlou", "flatmatt", "flatrob", "flathammock", "flatdhs", "flatdiscgolfbasket", "flatflashlight", "flatcats", "flatmurray", "flattypewriter", "flatvan", "flatrum"]], "1694149881.990207": ["v1ncenzo/4212/", "38.2346907778048", "-84.5461089493042", ["flatlou", "flatmatt", "flatrob", "flathammock", "flatdhs", "flatdiscgolfbasket", "flatflashlight", "flatcats", "flatmurray", "flattypewriter", "flatvan", "flatrum"]], "1694149881.9906585": ["1shemarine/9681/", "38.2347158313903", "-84.5457443744675", ["flatlou", "flatmatt", "flatrob", "flathammock", "flatdhs", "flatdiscgolfbasket", "flatflashlight", "flatcats", "flatmurray", "flattypewriter", "flatvan", "flatrum"]], "1694149881.9908996": ["v1ncenzo/4211/", "38.2347283581831", "-84.545562087002", ["flatlou", "flatmatt", "flatrob", "flathammock", "flatdhs", "flatdiscgolfbasket", "flatflashlight", "flatcats", "flatmurray", "flattypewriter", "flatvan", "flatrum"]], "1694149881.9921122": ["reart/2349/", "38.2345350675032", "-84.5462752987574", ["flatlou", "flatmatt", "flatrob", "flathammock", "flatdhs", "flatdiscgolfbasket", "flatflashlight", "flatcats", "flatmurray", "flattypewriter", "flatvan", "flatrum"]], "1694149881.9938235": ["pelicanrouge/6084/", "38.2343668304089", "-84.5466239340838", ["flatlou", "flatmatt", "flatrob", "flathammock", "flatdhs", "flatdiscgolfbasket", "flatflashlight", "flatcats", "flatmurray", "flattypewriter", "flatvan", "flatrum"]], "1694149881.9943628": ["1shemarine/10190/", "38.2343918839945", "-84.5462593608712", ["flatlou", "flatmatt", "flatrob", "flathammock", "flatdhs", "flatdiscgolfbasket", "flatflashlight", "flatcats", "flatmurray", "flattypewriter", "flatvan", "flatrum"]], "1694149881.9948258": ["aufbau/14290/", "38.23441693758", "-84.545894787533", ["flatlou", "flatmatt", "flatrob", "flathammock", "flatdhs", "flatdiscgolfbasket", "flatflashlight", "flatcats", "flatmurray", "flattypewriter", "flatvan", "flatrum"]], "1694149881.9950297": ["wanderingaus/27969/", "38.2344294643728", "-84.5457125008168", ["flatlou", "flatmatt", "flatrob", "flathammock", "flatdhs", "flatdiscgolfbasket", "flatflashlight", "flatcats", "flatmurray", "flattypewriter", "flatvan", "flatrum"]], "1694149881.995243": ["5star/8132/", "38.2344419911655", "-84.5455302140692", ["flatlou", "flatmatt", "flatrob", "flathammock", "flatdhs", "flatdiscgolfbasket", "flatflashlight", "flatcats", "flatmurray", "flattypewriter", "flatvan", "flatrum"]], "1694149881.995706": ["1shemarine/9592/", "38.2344670447511", "-84.5451656404798", ["flatlou", "flatmatt", "flatrob", "flathammock", "flatdhs", "flatdiscgolfbasket", "flatflashlight", "flatcats", "flatmurray", "flattypewriter", "flatvan", "flatrum"]], "1694149881.9959095": ["v1ncenzo/4205/", "38.2342236469002", "-84.5466079955106", ["flatlou", "flatmatt", "flatrob", "flathammock", "flatdhs", "flatdiscgolfbasket", "flatflashlight", "flatcats", "flatmurray", "flattypewriter", "flatvan", "flatrum"]], "1694149881.9961116": ["aufbau/15315/", "38.2342361736929", "-84.5464257092789", ["flatlou", "flatmatt", "flatrob", "flathammock", "flatdhs", "flatdiscgolfbasket", "flatflashlight", "flatcats", "flatmurray", "flattypewriter", "flatvan", "flatrum"]], "1694149881.996313": ["bojenris/187/", "38.2342487004857", "-84.5462434230158", ["flatlou", "flatmatt", "flatrob", "flathammock", "flatdhs", "flatdiscgolfbasket", "flatflashlight", "flatcats", "flatmurray", "flattypewriter", "flatvan", "flatrum"]], "1694149881.996512": ["citygalbex/5498/", "38.2342612272784", "-84.5460611367213", ["flatlou", "flatmatt", "flatrob", "flathammock", "flatdhs", "flatdiscgolfbasket", "flatflashlight", "flatcats", "flatmurray", "flattypewriter", "flatvan", "flatrum"]], "1694149881.9967444": ["ponian/2665/", "38.2342737540712", "-84.5458788503955", ["flatlou", "flatmatt", "flatrob", "flathammock", "flatdhs", "flatdiscgolfbasket", "flatflashlight", "flatcats", "flatmurray", "flattypewriter", "flatvan", "flatrum"]], "1694149881.9969287": ["1shemarine/9709/", "38.234286280864", "-84.5456965640382", ["flatlou", "flatmatt", "flatrob", "flathammock", "flatdhs", "flatdiscgolfbasket", "flatflashlight", "flatcats", "flatmurray", "flattypewriter", "flatvan", "flatrum"]], "1694149881.997117": ["buckeyecacher111/11348/", "38.2342988076567", "-84.5455142776495", ["flatlou", "flatmatt", "flatrob", "flathammock", "flatdhs", "flatdiscgolfbasket", "flatflashlight", "flatcats", "flatmurray", "flattypewriter", "flatvan", "flatrum"]], "1694149881.997602": ["bisquick2/4775/", "38.2343238612423", "-84.5451497047779", ["flatlou", "flatmatt", "flatrob", "flathammock", "flatdhs", "flatdiscgolfbasket", "flatflashlight", "flatcats", "flatmurray", "flattypewriter", "flatvan", "flatrum"]], "1694149881.9980755": ["searays2/772/", "38.2340929901842", "-84.5464097710965", ["flatlou", "flatmatt", "flatrob", "flathammock", "flatdhs", "flatdiscgolfbasket", "flatflashlight", "flatcats", "flatmurray", "flattypewriter", "flatvan", "flatrum"]], "1694149881.9982772": ["vamtrix/4921/", "38.2341055169769", "-84.5462274851923", ["flatlou", "flatmatt", "flatrob", "flathammock", "flatdhs", "flatdiscgolfbasket", "flatflashlight", "flatcats", "flatmurray", "flattypewriter", "flatvan", "flatrum"]], "1694149881.9989676": ["ysop/289/", "38.2341430973552", "-84.5456806272915", ["flatlou", "flatmatt", "flatrob", "flathammock", "flatdhs", "flatdiscgolfbasket", "flatflashlight", "flatcats", "flatmurray", "flattypewriter", "flatvan", "flatrum"]], "1694149881.9996786": ["bonnieb1/3968/", "38.2341806777335", "-84.545133769108", ["flatlou", "flatmatt", "flatrob", "flathammock", "flatdhs", "flatdiscgolfbasket", "flatflashlight", "flatcats", "flatmurray", "flattypewriter", "flatvan", "flatrum"]]}}